{
  "date": "2025-10-11",
  "projects": {
    "cdp.aleoudev.fr (Workspace)": {
      "totalLinesAdded": 1809,
      "totalLinesRemoved": 14,
      "totalActiveTime": 19,
      "files": {
        "c:\\Mes Projets\\www\\iis\\cdp.aleoudev.fr\\xdev\\api\\synchro-eventscop\\includes\\tools.asp": [
          {
            "timestamp": "2025-10-10T22:00:49.361Z",
            "fileName": "c:\\Mes Projets\\www\\iis\\cdp.aleoudev.fr\\xdev\\api\\synchro-eventscop\\includes\\tools.asp",
            "fileType": ".asp",
            "linesAdded": 432,
            "linesRemoved": 0,
            "projectName": "cdp.aleoudev.fr (Workspace)",
            "content": {
              "added": [],
              "removed": []
            },
            "duration": 4,
            "language": "asp"
          },
          {
            "timestamp": "2025-10-10T22:00:55.169Z",
            "fileName": "c:\\Mes Projets\\www\\iis\\cdp.aleoudev.fr\\xdev\\api\\synchro-eventscop\\includes\\tools.asp",
            "fileType": ".asp",
            "linesAdded": 32,
            "linesRemoved": 0,
            "projectName": "cdp.aleoudev.fr (Workspace)",
            "content": {
              "added": [],
              "removed": []
            },
            "duration": 1,
            "language": "asp"
          }
        ],
        "c:\\Mes Projets\\www\\iis\\cdp.aleoudev.fr\\xdev\\api\\synchro-eventscop\\includes\\functions.asp": [
          {
            "timestamp": "2025-10-10T22:04:11.371Z",
            "fileName": "c:\\Mes Projets\\www\\iis\\cdp.aleoudev.fr\\xdev\\api\\synchro-eventscop\\includes\\functions.asp",
            "fileType": ".asp",
            "linesAdded": 0,
            "linesRemoved": 14,
            "projectName": "cdp.aleoudev.fr (Workspace)",
            "content": {
              "added": [],
              "removed": []
            },
            "duration": 4,
            "language": "asp"
          }
        ],
        "c:\\Mes Projets\\www\\iis\\cdp.aleoudev.fr\\xdev\\api\\synchro-eventscop\\modules\\etab_queries_tmp\\functions.asp": [
          {
            "timestamp": "2025-10-10T22:05:19.754Z",
            "fileName": "c:\\Mes Projets\\www\\iis\\cdp.aleoudev.fr\\xdev\\api\\synchro-eventscop\\modules\\etab_queries_tmp\\functions.asp",
            "fileType": ".asp",
            "linesAdded": 4,
            "linesRemoved": 0,
            "projectName": "cdp.aleoudev.fr (Workspace)",
            "content": {
              "added": [],
              "removed": []
            },
            "duration": 2,
            "language": "asp"
          }
        ],
        "c:\\Mes Projets\\www\\iis\\cdp.aleoudev.fr\\xdev\\api\\synchro-eventscop\\modules\\etab_queries\\functions.asp": [
          {
            "timestamp": "2025-10-10T22:05:39.022Z",
            "fileName": "c:\\Mes Projets\\www\\iis\\cdp.aleoudev.fr\\xdev\\api\\synchro-eventscop\\modules\\etab_queries\\functions.asp",
            "fileType": ".asp",
            "linesAdded": 716,
            "linesRemoved": 0,
            "projectName": "cdp.aleoudev.fr (Workspace)",
            "content": {
              "added": [],
              "removed": []
            },
            "duration": 1,
            "language": "asp"
          }
        ],
        "c:\\Mes Projets\\www\\iis\\cdp.aleoudev.fr\\xdev\\api\\synchro-eventscop\\modules\\etab\\functions.asp": [
          {
            "timestamp": "2025-10-10T22:11:32.827Z",
            "fileName": "c:\\Mes Projets\\www\\iis\\cdp.aleoudev.fr\\xdev\\api\\synchro-eventscop\\modules\\etab\\functions.asp",
            "fileType": ".asp",
            "linesAdded": 542,
            "linesRemoved": 0,
            "projectName": "cdp.aleoudev.fr (Workspace)",
            "content": {
              "added": [],
              "removed": []
            },
            "duration": 0,
            "language": "asp"
          },
          {
            "timestamp": "2025-10-10T22:15:43.622Z",
            "fileName": "c:\\Mes Projets\\www\\iis\\cdp.aleoudev.fr\\xdev\\api\\synchro-eventscop\\modules\\etab\\functions.asp",
            "fileType": ".asp",
            "linesAdded": 79,
            "linesRemoved": 0,
            "projectName": "cdp.aleoudev.fr (Workspace)",
            "content": {
              "added": [],
              "removed": []
            },
            "duration": 5,
            "language": "asp"
          },
          {
            "timestamp": "2025-10-10T22:16:52.239Z",
            "fileName": "c:\\Mes Projets\\www\\iis\\cdp.aleoudev.fr\\xdev\\api\\synchro-eventscop\\modules\\etab\\functions.asp",
            "fileType": ".asp",
            "linesAdded": 4,
            "linesRemoved": 0,
            "projectName": "cdp.aleoudev.fr (Workspace)",
            "content": {
              "added": [],
              "removed": []
            },
            "duration": 2,
            "language": "asp"
          }
        ]
      },
      "languageStats": {
        "asp": 9
      },
      "changeFrequency": {
        "0": 9
      },
      "topFiles": [
        "c:\\Mes Projets\\www\\iis\\cdp.aleoudev.fr\\xdev\\api\\synchro-eventscop\\includes\\tools.asp",
        "c:\\Mes Projets\\www\\iis\\cdp.aleoudev.fr\\xdev\\api\\synchro-eventscop\\includes\\functions.asp"
      ],
      "averageChangeSize": 159.33333333333334
    },
    "eventscop-frontend-guide (Workspace)": {
      "totalLinesAdded": 1024,
      "totalLinesRemoved": 6,
      "totalActiveTime": 23,
      "files": {
        "c:\\Mes Projets\\EventScop\\eventscop-frontend-guide\\src\\app\\[locale]\\[category_slug]\\[[...url_path]]\\page.tsx": [
          {
            "timestamp": "2025-10-10T22:26:22.610Z",
            "fileName": "c:\\Mes Projets\\EventScop\\eventscop-frontend-guide\\src\\app\\[locale]\\[category_slug]\\[[...url_path]]\\page.tsx",
            "fileType": ".tsx",
            "linesAdded": 404,
            "linesRemoved": 0,
            "projectName": "eventscop-frontend-guide (Workspace)",
            "content": {
              "added": [],
              "removed": []
            },
            "duration": 0,
            "language": "tsx"
          },
          {
            "timestamp": "2025-10-10T22:32:00.743Z",
            "fileName": "c:\\Mes Projets\\EventScop\\eventscop-frontend-guide\\src\\app\\[locale]\\[category_slug]\\[[...url_path]]\\page.tsx",
            "fileType": ".tsx",
            "linesAdded": 0,
            "linesRemoved": 2,
            "projectName": "eventscop-frontend-guide (Workspace)",
            "content": {
              "added": [],
              "removed": []
            },
            "duration": 0,
            "language": "tsx"
          },
          {
            "timestamp": "2025-10-10T22:33:07.433Z",
            "fileName": "c:\\Mes Projets\\EventScop\\eventscop-frontend-guide\\src\\app\\[locale]\\[category_slug]\\[[...url_path]]\\page.tsx",
            "fileType": ".tsx",
            "linesAdded": 2,
            "linesRemoved": 0,
            "projectName": "eventscop-frontend-guide (Workspace)",
            "content": {
              "added": [],
              "removed": []
            },
            "duration": 2,
            "language": "tsx"
          }
        ],
        "c:\\Mes Projets\\EventScop\\eventscop-frontend-guide\\src\\components\\place\\PlaceQuoteSidebar.tsx": [
          {
            "timestamp": "2025-10-10T22:36:53.218Z",
            "fileName": "c:\\Mes Projets\\EventScop\\eventscop-frontend-guide\\src\\components\\place\\PlaceQuoteSidebar.tsx",
            "fileType": ".tsx",
            "linesAdded": 68,
            "linesRemoved": 0,
            "projectName": "eventscop-frontend-guide (Workspace)",
            "content": {
              "added": [],
              "removed": []
            },
            "duration": 4,
            "language": "tsx"
          }
        ],
        "c:\\Mes Projets\\EventScop\\eventscop-frontend-guide\\src\\components\\common\\quote-sidebar\\PlaceQuoteForm.tsx": [
          {
            "timestamp": "2025-10-10T22:40:55.722Z",
            "fileName": "c:\\Mes Projets\\EventScop\\eventscop-frontend-guide\\src\\components\\common\\quote-sidebar\\PlaceQuoteForm.tsx",
            "fileType": ".tsx",
            "linesAdded": 72,
            "linesRemoved": 0,
            "projectName": "eventscop-frontend-guide (Workspace)",
            "content": {
              "added": [],
              "removed": []
            },
            "duration": 5,
            "language": "tsx"
          },
          {
            "timestamp": "2025-10-10T22:41:01.624Z",
            "fileName": "c:\\Mes Projets\\EventScop\\eventscop-frontend-guide\\src\\components\\common\\quote-sidebar\\PlaceQuoteForm.tsx",
            "fileType": ".tsx",
            "linesAdded": 1,
            "linesRemoved": 0,
            "projectName": "eventscop-frontend-guide (Workspace)",
            "content": {
              "added": [],
              "removed": []
            },
            "duration": 1,
            "language": "tsx"
          }
        ],
        "c:\\Users\\Julien\\AppData\\Roaming\\Code\\User\\settings.json": [
          {
            "timestamp": "2025-10-10T22:45:30.355Z",
            "fileName": "c:\\Users\\Julien\\AppData\\Roaming\\Code\\User\\settings.json",
            "fileType": ".json",
            "linesAdded": 295,
            "linesRemoved": 0,
            "projectName": "eventscop-frontend-guide (Workspace)",
            "content": {
              "added": [],
              "removed": []
            },
            "duration": 5,
            "language": "json"
          }
        ],
        "c:\\Mes Projets\\EventScop\\eventscop-frontend-guide\\src\\components\\common\\quote-sidebar\\QuoteTarifs.tsx": [
          {
            "timestamp": "2025-10-10T22:45:58.957Z",
            "fileName": "c:\\Mes Projets\\EventScop\\eventscop-frontend-guide\\src\\components\\common\\quote-sidebar\\QuoteTarifs.tsx",
            "fileType": ".tsx",
            "linesAdded": 50,
            "linesRemoved": 0,
            "projectName": "eventscop-frontend-guide (Workspace)",
            "content": {
              "added": [],
              "removed": []
            },
            "duration": 1,
            "language": "tsx"
          },
          {
            "timestamp": "2025-10-10T22:47:03.540Z",
            "fileName": "c:\\Mes Projets\\EventScop\\eventscop-frontend-guide\\src\\components\\common\\quote-sidebar\\QuoteTarifs.tsx",
            "fileType": ".tsx",
            "linesAdded": 0,
            "linesRemoved": 2,
            "projectName": "eventscop-frontend-guide (Workspace)",
            "content": {
              "added": [],
              "removed": []
            },
            "duration": 2,
            "language": "tsx"
          },
          {
            "timestamp": "2025-10-10T22:48:33.113Z",
            "fileName": "c:\\Mes Projets\\EventScop\\eventscop-frontend-guide\\src\\components\\common\\quote-sidebar\\QuoteTarifs.tsx",
            "fileType": ".tsx",
            "linesAdded": 2,
            "linesRemoved": 0,
            "projectName": "eventscop-frontend-guide (Workspace)",
            "content": {
              "added": [],
              "removed": []
            },
            "duration": 2,
            "language": "tsx"
          }
        ],
        "c:\\Mes Projets\\EventScop\\eventscop-frontend-guide\\src\\components\\common\\quote-sidebar\\PlaceQuoteButton.tsx": [
          {
            "timestamp": "2025-10-10T22:55:22.582Z",
            "fileName": "c:\\Mes Projets\\EventScop\\eventscop-frontend-guide\\src\\components\\common\\quote-sidebar\\PlaceQuoteButton.tsx",
            "fileType": ".tsx",
            "linesAdded": 60,
            "linesRemoved": 0,
            "projectName": "eventscop-frontend-guide (Workspace)",
            "content": {
              "added": [],
              "removed": []
            },
            "duration": 0,
            "language": "tsx"
          }
        ],
        "c:\\Mes Projets\\EventScop\\eventscop-frontend-guide\\src\\components\\common\\quote-sidebar\\ContactButtons.tsx": [
          {
            "timestamp": "2025-10-10T23:01:28.664Z",
            "fileName": "c:\\Mes Projets\\EventScop\\eventscop-frontend-guide\\src\\components\\common\\quote-sidebar\\ContactButtons.tsx",
            "fileType": ".tsx",
            "linesAdded": 0,
            "linesRemoved": 2,
            "projectName": "eventscop-frontend-guide (Workspace)",
            "content": {
              "added": [],
              "removed": []
            },
            "duration": 0,
            "language": "tsx"
          },
          {
            "timestamp": "2025-10-10T23:02:21.225Z",
            "fileName": "c:\\Mes Projets\\EventScop\\eventscop-frontend-guide\\src\\components\\common\\quote-sidebar\\ContactButtons.tsx",
            "fileType": ".tsx",
            "linesAdded": 2,
            "linesRemoved": 0,
            "projectName": "eventscop-frontend-guide (Workspace)",
            "content": {
              "added": [],
              "removed": []
            },
            "duration": 1,
            "language": "tsx"
          },
          {
            "timestamp": "2025-10-10T23:07:47.092Z",
            "fileName": "c:\\Mes Projets\\EventScop\\eventscop-frontend-guide\\src\\components\\common\\quote-sidebar\\ContactButtons.tsx",
            "fileType": ".tsx",
            "linesAdded": 5,
            "linesRemoved": 0,
            "projectName": "eventscop-frontend-guide (Workspace)",
            "content": {
              "added": [],
              "removed": []
            },
            "duration": 0,
            "language": "tsx"
          },
          {
            "timestamp": "2025-10-10T23:15:53.259Z",
            "fileName": "c:\\Mes Projets\\EventScop\\eventscop-frontend-guide\\src\\components\\common\\quote-sidebar\\ContactButtons.tsx",
            "fileType": ".tsx",
            "linesAdded": 63,
            "linesRemoved": 0,
            "projectName": "eventscop-frontend-guide (Workspace)",
            "content": {
              "added": [],
              "removed": []
            },
            "duration": 0,
            "language": "tsx"
          }
        ]
      },
      "languageStats": {
        "tsx": 0
      },
      "changeFrequency": {
        "0": 0
      },
      "topFiles": [
        "c:\\Mes Projets\\EventScop\\eventscop-frontend-guide\\src\\app\\[locale]\\[category_slug]\\[[...url_path]]\\page.tsx"
      ],
      "averageChangeSize": 404
    }
  },
  "totalActiveTime": 9,
  "totalProjects": 1,
  "totalFiles": 2,
  "mostActiveHours": [
    0
  ],
  "mostUsedLanguages": [
    "asp"
  ]
}