{
  "date": "2025-11-25",
  "projects": {
    "eventscop-api-guide (Workspace)": {
      "totalLinesAdded": 2451,
      "totalLinesRemoved": 113,
      "totalActiveTime": 10,
      "files": {
        "c:\\Mes Projets\\EventScop\\eventscop-api-guide\\eventscop_utils\\models\\SupplierRseLabel.py": [
          {
            "timestamp": "2025-11-24T23:03:57.602Z",
            "fileName": "c:\\Mes Projets\\EventScop\\eventscop-api-guide\\eventscop_utils\\models\\SupplierRseLabel.py",
            "fileType": ".py",
            "linesAdded": 55,
            "linesRemoved": 0,
            "projectName": "eventscop-api-guide (Workspace)",
            "content": {
              "added": [],
              "removed": []
            },
            "duration": 0,
            "language": "py"
          }
        ],
        "c:\\Mes Projets\\EventScop\\eventscop-api-guide\\migration\\versions\\052ff740ad34_add_missing_indexes_for_search_.py": [
          {
            "timestamp": "2025-11-24T23:06:13.969Z",
            "fileName": "c:\\Mes Projets\\EventScop\\eventscop-api-guide\\migration\\versions\\052ff740ad34_add_missing_indexes_for_search_.py",
            "fileType": ".py",
            "linesAdded": 158,
            "linesRemoved": 0,
            "projectName": "eventscop-api-guide (Workspace)",
            "content": {
              "added": [],
              "removed": []
            },
            "duration": 3,
            "language": "py"
          },
          {
            "timestamp": "2025-11-24T23:06:27.409Z",
            "fileName": "c:\\Mes Projets\\EventScop\\eventscop-api-guide\\migration\\versions\\052ff740ad34_add_missing_indexes_for_search_.py",
            "fileType": ".py",
            "linesAdded": 0,
            "linesRemoved": 52,
            "projectName": "eventscop-api-guide (Workspace)",
            "content": {
              "added": [],
              "removed": []
            },
            "duration": 1,
            "language": "py"
          },
          {
            "timestamp": "2025-11-24T23:07:08.844Z",
            "fileName": "c:\\Mes Projets\\EventScop\\eventscop-api-guide\\migration\\versions\\052ff740ad34_add_missing_indexes_for_search_.py",
            "fileType": ".py",
            "linesAdded": 0,
            "linesRemoved": 60,
            "projectName": "eventscop-api-guide (Workspace)",
            "content": {
              "added": [],
              "removed": []
            },
            "duration": 1,
            "language": "py"
          }
        ],
        "c:\\Mes Projets\\EventScop\\eventscop-api-guide\\app\\modules\\suppliers\\activities\\routes.py": [
          {
            "timestamp": "2025-11-24T23:07:37.439Z",
            "fileName": "c:\\Mes Projets\\EventScop\\eventscop-api-guide\\app\\modules\\suppliers\\activities\\routes.py",
            "fileType": ".py",
            "linesAdded": 905,
            "linesRemoved": 0,
            "projectName": "eventscop-api-guide (Workspace)",
            "content": {
              "added": [],
              "removed": []
            },
            "duration": 1,
            "language": "py"
          }
        ],
        "c:\\Mes Projets\\EventScop\\eventscop-api-guide\\app\\modules\\cities\\routes.py": [
          {
            "timestamp": "2025-11-25T12:43:43.428Z",
            "fileName": "c:\\Mes Projets\\EventScop\\eventscop-api-guide\\app\\modules\\cities\\routes.py",
            "fileType": ".py",
            "linesAdded": 618,
            "linesRemoved": 0,
            "projectName": "eventscop-api-guide (Workspace)",
            "content": {
              "added": [],
              "removed": []
            },
            "duration": 0,
            "language": "py"
          },
          {
            "timestamp": "2025-11-25T12:45:34.306Z",
            "fileName": "c:\\Mes Projets\\EventScop\\eventscop-api-guide\\app\\modules\\cities\\routes.py",
            "fileType": ".py",
            "linesAdded": 107,
            "linesRemoved": 0,
            "projectName": "eventscop-api-guide (Workspace)",
            "content": {
              "added": [],
              "removed": []
            },
            "duration": 2,
            "language": "py"
          }
        ],
        "c:\\Mes Projets\\EventScop\\eventscop-api-guide\\app\\modules\\seminars\\routes.py": [
          {
            "timestamp": "2025-11-25T12:53:13.760Z",
            "fileName": "c:\\Mes Projets\\EventScop\\eventscop-api-guide\\app\\modules\\seminars\\routes.py",
            "fileType": ".py",
            "linesAdded": 605,
            "linesRemoved": 0,
            "projectName": "eventscop-api-guide (Workspace)",
            "content": {
              "added": [],
              "removed": []
            },
            "duration": 0,
            "language": "py"
          },
          {
            "timestamp": "2025-11-25T12:54:16.793Z",
            "fileName": "c:\\Mes Projets\\EventScop\\eventscop-api-guide\\app\\modules\\seminars\\routes.py",
            "fileType": ".py",
            "linesAdded": 2,
            "linesRemoved": 0,
            "projectName": "eventscop-api-guide (Workspace)",
            "content": {
              "added": [],
              "removed": []
            },
            "duration": 2,
            "language": "py"
          },
          {
            "timestamp": "2025-11-25T15:12:14.473Z",
            "fileName": "c:\\Mes Projets\\EventScop\\eventscop-api-guide\\app\\modules\\seminars\\routes.py",
            "fileType": ".py",
            "linesAdded": 0,
            "linesRemoved": 1,
            "projectName": "eventscop-api-guide (Workspace)",
            "content": {
              "added": [],
              "removed": []
            },
            "duration": 0,
            "language": "py"
          },
          {
            "timestamp": "2025-11-25T15:19:33.109Z",
            "fileName": "c:\\Mes Projets\\EventScop\\eventscop-api-guide\\app\\modules\\seminars\\routes.py",
            "fileType": ".py",
            "linesAdded": 1,
            "linesRemoved": 0,
            "projectName": "eventscop-api-guide (Workspace)",
            "content": {
              "added": [],
              "removed": []
            },
            "duration": 0,
            "language": "py"
          }
        ]
      },
      "languageStats": {
        "py": 6
      },
      "changeFrequency": {
        "0": 6
      },
      "topFiles": [
        "c:\\Mes Projets\\EventScop\\eventscop-api-guide\\migration\\versions\\052ff740ad34_add_missing_indexes_for_search_.py",
        "c:\\Mes Projets\\EventScop\\eventscop-api-guide\\eventscop_utils\\models\\SupplierRseLabel.py",
        "c:\\Mes Projets\\EventScop\\eventscop-api-guide\\app\\modules\\suppliers\\activities\\routes.py"
      ],
      "averageChangeSize": 246
    },
    "eventscop-frontend-guide (Workspace)": {
      "totalLinesAdded": 4243,
      "totalLinesRemoved": 239,
      "totalActiveTime": 162,
      "files": {
        "c:\\Mes Projets\\EventScop\\eventscop-frontend-guide\\.next\\package.json": [
          {
            "timestamp": "2025-11-25T08:26:00.338Z",
            "fileName": "c:\\Mes Projets\\EventScop\\eventscop-frontend-guide\\.next\\package.json",
            "fileType": ".json",
            "linesAdded": 3,
            "linesRemoved": 0,
            "projectName": "eventscop-frontend-guide (Workspace)",
            "content": {
              "added": [],
              "removed": []
            },
            "duration": 0,
            "language": "json"
          },
          {
            "timestamp": "2025-11-25T08:26:02.376Z",
            "fileName": "c:\\Mes Projets\\EventScop\\eventscop-frontend-guide\\.next\\package.json",
            "fileType": ".json",
            "linesAdded": 0,
            "linesRemoved": 2,
            "projectName": "eventscop-frontend-guide (Workspace)",
            "content": {
              "added": [],
              "removed": []
            },
            "duration": 1,
            "language": "json"
          }
        ],
        "c:\\Mes Projets\\EventScop\\eventscop-frontend-guide\\src\\app\\sitemap-activities.xml\\route.ts": [
          {
            "timestamp": "2025-11-25T08:50:58.827Z",
            "fileName": "c:\\Mes Projets\\EventScop\\eventscop-frontend-guide\\src\\app\\sitemap-activities.xml\\route.ts",
            "fileType": ".ts",
            "linesAdded": 73,
            "linesRemoved": 0,
            "projectName": "eventscop-frontend-guide (Workspace)",
            "content": {
              "added": [],
              "removed": []
            },
            "duration": 0,
            "language": "ts"
          },
          {
            "timestamp": "2025-11-25T08:51:12.663Z",
            "fileName": "c:\\Mes Projets\\EventScop\\eventscop-frontend-guide\\src\\app\\sitemap-activities.xml\\route.ts",
            "fileType": ".ts",
            "linesAdded": 1,
            "linesRemoved": 0,
            "projectName": "eventscop-frontend-guide (Workspace)",
            "content": {
              "added": [],
              "removed": []
            },
            "duration": 1,
            "language": "ts"
          },
          {
            "timestamp": "2025-11-25T08:51:21.864Z",
            "fileName": "c:\\Mes Projets\\EventScop\\eventscop-frontend-guide\\src\\app\\sitemap-activities.xml\\route.ts",
            "fileType": ".ts",
            "linesAdded": 0,
            "linesRemoved": 1,
            "projectName": "eventscop-frontend-guide (Workspace)",
            "content": {
              "added": [],
              "removed": []
            },
            "duration": 1,
            "language": "ts"
          }
        ],
        "c:\\Mes Projets\\EventScop\\eventscop-frontend-guide\\lefthook.yml": [
          {
            "timestamp": "2025-11-25T08:52:13.108Z",
            "fileName": "c:\\Mes Projets\\EventScop\\eventscop-frontend-guide\\lefthook.yml",
            "fileType": ".yml",
            "linesAdded": 22,
            "linesRemoved": 0,
            "projectName": "eventscop-frontend-guide (Workspace)",
            "content": {
              "added": [],
              "removed": []
            },
            "duration": 1,
            "language": "yml"
          },
          {
            "timestamp": "2025-11-25T08:54:07.741Z",
            "fileName": "c:\\Mes Projets\\EventScop\\eventscop-frontend-guide\\lefthook.yml",
            "fileType": ".yml",
            "linesAdded": 0,
            "linesRemoved": 8,
            "projectName": "eventscop-frontend-guide (Workspace)",
            "content": {
              "added": [],
              "removed": []
            },
            "duration": 2,
            "language": "yml"
          },
          {
            "timestamp": "2025-11-25T08:54:58.723Z",
            "fileName": "c:\\Mes Projets\\EventScop\\eventscop-frontend-guide\\lefthook.yml",
            "fileType": ".yml",
            "linesAdded": 8,
            "linesRemoved": 0,
            "projectName": "eventscop-frontend-guide (Workspace)",
            "content": {
              "added": [],
              "removed": []
            },
            "duration": 1,
            "language": "yml"
          },
          {
            "timestamp": "2025-11-25T14:54:39.588Z",
            "fileName": "c:\\Mes Projets\\EventScop\\eventscop-frontend-guide\\lefthook.yml",
            "fileType": ".yml",
            "linesAdded": 0,
            "linesRemoved": 9,
            "projectName": "eventscop-frontend-guide (Workspace)",
            "content": {
              "added": [],
              "removed": []
            },
            "duration": 3,
            "language": "yml"
          },
          {
            "timestamp": "2025-11-25T14:55:01.393Z",
            "fileName": "c:\\Mes Projets\\EventScop\\eventscop-frontend-guide\\lefthook.yml",
            "fileType": ".yml",
            "linesAdded": 9,
            "linesRemoved": 0,
            "projectName": "eventscop-frontend-guide (Workspace)",
            "content": {
              "added": [],
              "removed": []
            },
            "duration": 1,
            "language": "yml"
          }
        ],
        "c:\\Mes Projets\\EventScop\\eventscop-frontend-guide\\eventscop-frontend-guide.code-workspace": [
          {
            "timestamp": "2025-11-25T08:58:28.123Z",
            "fileName": "c:\\Mes Projets\\EventScop\\eventscop-frontend-guide\\eventscop-frontend-guide.code-workspace",
            "fileType": ".code-workspace",
            "linesAdded": 45,
            "linesRemoved": 0,
            "projectName": "eventscop-frontend-guide (Workspace)",
            "content": {
              "added": [],
              "removed": []
            },
            "duration": 4,
            "language": "code-workspace"
          }
        ],
        "c:\\Mes Projets\\EventScop\\eventscop-frontend-guide\\.next\\types\\validator.ts": [
          {
            "timestamp": "2025-11-25T13:13:01.470Z",
            "fileName": "c:\\Mes Projets\\EventScop\\eventscop-frontend-guide\\.next\\types\\validator.ts",
            "fileType": ".ts",
            "linesAdded": 737,
            "linesRemoved": 0,
            "projectName": "eventscop-frontend-guide (Workspace)",
            "content": {
              "added": [],
              "removed": []
            },
            "duration": 0,
            "language": "ts"
          }
        ],
        "c:\\Mes Projets\\EventScop\\eventscop-frontend-guide\\src\\components\\ui\\CityAutocomplete.tsx": [
          {
            "timestamp": "2025-11-25T13:18:54.651Z",
            "fileName": "c:\\Mes Projets\\EventScop\\eventscop-frontend-guide\\src\\components\\ui\\CityAutocomplete.tsx",
            "fileType": ".tsx",
            "linesAdded": 250,
            "linesRemoved": 0,
            "projectName": "eventscop-frontend-guide (Workspace)",
            "content": {
              "added": [],
              "removed": []
            },
            "duration": 0,
            "language": "tsx"
          },
          {
            "timestamp": "2025-11-25T13:19:17.269Z",
            "fileName": "c:\\Mes Projets\\EventScop\\eventscop-frontend-guide\\src\\components\\ui\\CityAutocomplete.tsx",
            "fileType": ".tsx",
            "linesAdded": 1,
            "linesRemoved": 0,
            "projectName": "eventscop-frontend-guide (Workspace)",
            "content": {
              "added": [],
              "removed": []
            },
            "duration": 1,
            "language": "tsx"
          },
          {
            "timestamp": "2025-11-25T13:21:44.293Z",
            "fileName": "c:\\Mes Projets\\EventScop\\eventscop-frontend-guide\\src\\components\\ui\\CityAutocomplete.tsx",
            "fileType": ".tsx",
            "linesAdded": 1,
            "linesRemoved": 0,
            "projectName": "eventscop-frontend-guide (Workspace)",
            "content": {
              "added": [],
              "removed": []
            },
            "duration": 3,
            "language": "tsx"
          },
          {
            "timestamp": "2025-11-25T13:22:00.134Z",
            "fileName": "c:\\Mes Projets\\EventScop\\eventscop-frontend-guide\\src\\components\\ui\\CityAutocomplete.tsx",
            "fileType": ".tsx",
            "linesAdded": 7,
            "linesRemoved": 0,
            "projectName": "eventscop-frontend-guide (Workspace)",
            "content": {
              "added": [],
              "removed": []
            },
            "duration": 1,
            "language": "tsx"
          },
          {
            "timestamp": "2025-11-25T13:26:48.693Z",
            "fileName": "c:\\Mes Projets\\EventScop\\eventscop-frontend-guide\\src\\components\\ui\\CityAutocomplete.tsx",
            "fileType": ".tsx",
            "linesAdded": 2,
            "linesRemoved": 0,
            "projectName": "eventscop-frontend-guide (Workspace)",
            "content": {
              "added": [],
              "removed": []
            },
            "duration": 5,
            "language": "tsx"
          }
        ],
        "c:\\Mes Projets\\EventScop\\eventscop-frontend-guide\\src\\components\\common\\quote-sidebar\\ActivityQuoteForm.tsx": [
          {
            "timestamp": "2025-11-25T13:37:53.946Z",
            "fileName": "c:\\Mes Projets\\EventScop\\eventscop-frontend-guide\\src\\components\\common\\quote-sidebar\\ActivityQuoteForm.tsx",
            "fileType": ".tsx",
            "linesAdded": 160,
            "linesRemoved": 0,
            "projectName": "eventscop-frontend-guide (Workspace)",
            "content": {
              "added": [],
              "removed": []
            },
            "duration": 0,
            "language": "tsx"
          },
          {
            "timestamp": "2025-11-25T13:41:00.693Z",
            "fileName": "c:\\Mes Projets\\EventScop\\eventscop-frontend-guide\\src\\components\\common\\quote-sidebar\\ActivityQuoteForm.tsx",
            "fileType": ".tsx",
            "linesAdded": 1,
            "linesRemoved": 0,
            "projectName": "eventscop-frontend-guide (Workspace)",
            "content": {
              "added": [],
              "removed": []
            },
            "duration": 4,
            "language": "tsx"
          },
          {
            "timestamp": "2025-11-25T13:47:05.304Z",
            "fileName": "c:\\Mes Projets\\EventScop\\eventscop-frontend-guide\\src\\components\\common\\quote-sidebar\\ActivityQuoteForm.tsx",
            "fileType": ".tsx",
            "linesAdded": 1,
            "linesRemoved": 0,
            "projectName": "eventscop-frontend-guide (Workspace)",
            "content": {
              "added": [],
              "removed": []
            },
            "duration": 1,
            "language": "tsx"
          },
          {
            "timestamp": "2025-11-25T13:52:44.851Z",
            "fileName": "c:\\Mes Projets\\EventScop\\eventscop-frontend-guide\\src\\components\\common\\quote-sidebar\\ActivityQuoteForm.tsx",
            "fileType": ".tsx",
            "linesAdded": 0,
            "linesRemoved": 1,
            "projectName": "eventscop-frontend-guide (Workspace)",
            "content": {
              "added": [],
              "removed": []
            },
            "duration": 1,
            "language": "tsx"
          },
          {
            "timestamp": "2025-11-25T14:27:04.900Z",
            "fileName": "c:\\Mes Projets\\EventScop\\eventscop-frontend-guide\\src\\components\\common\\quote-sidebar\\ActivityQuoteForm.tsx",
            "fileType": ".tsx",
            "linesAdded": 7,
            "linesRemoved": 0,
            "projectName": "eventscop-frontend-guide (Workspace)",
            "content": {
              "added": [],
              "removed": []
            },
            "duration": 0,
            "language": "tsx"
          },
          {
            "timestamp": "2025-11-25T14:28:10.980Z",
            "fileName": "c:\\Mes Projets\\EventScop\\eventscop-frontend-guide\\src\\components\\common\\quote-sidebar\\ActivityQuoteForm.tsx",
            "fileType": ".tsx",
            "linesAdded": 2,
            "linesRemoved": 0,
            "projectName": "eventscop-frontend-guide (Workspace)",
            "content": {
              "added": [],
              "removed": []
            },
            "duration": 2,
            "language": "tsx"
          },
          {
            "timestamp": "2025-11-25T14:29:07.104Z",
            "fileName": "c:\\Mes Projets\\EventScop\\eventscop-frontend-guide\\src\\components\\common\\quote-sidebar\\ActivityQuoteForm.tsx",
            "fileType": ".tsx",
            "linesAdded": 1,
            "linesRemoved": 0,
            "projectName": "eventscop-frontend-guide (Workspace)",
            "content": {
              "added": [],
              "removed": []
            },
            "duration": 1,
            "language": "tsx"
          },
          {
            "timestamp": "2025-11-25T14:37:28.748Z",
            "fileName": "c:\\Mes Projets\\EventScop\\eventscop-frontend-guide\\src\\components\\common\\quote-sidebar\\ActivityQuoteForm.tsx",
            "fileType": ".tsx",
            "linesAdded": 2,
            "linesRemoved": 0,
            "projectName": "eventscop-frontend-guide (Workspace)",
            "content": {
              "added": [],
              "removed": []
            },
            "duration": 2,
            "language": "tsx"
          },
          {
            "timestamp": "2025-11-25T14:40:57.703Z",
            "fileName": "c:\\Mes Projets\\EventScop\\eventscop-frontend-guide\\src\\components\\common\\quote-sidebar\\ActivityQuoteForm.tsx",
            "fileType": ".tsx",
            "linesAdded": 2,
            "linesRemoved": 0,
            "projectName": "eventscop-frontend-guide (Workspace)",
            "content": {
              "added": [],
              "removed": []
            },
            "duration": 4,
            "language": "tsx"
          },
          {
            "timestamp": "2025-11-25T14:43:56.959Z",
            "fileName": "c:\\Mes Projets\\EventScop\\eventscop-frontend-guide\\src\\components\\common\\quote-sidebar\\ActivityQuoteForm.tsx",
            "fileType": ".tsx",
            "linesAdded": 2,
            "linesRemoved": 0,
            "projectName": "eventscop-frontend-guide (Workspace)",
            "content": {
              "added": [],
              "removed": []
            },
            "duration": 1,
            "language": "tsx"
          },
          {
            "timestamp": "2025-11-25T14:46:24.784Z",
            "fileName": "c:\\Mes Projets\\EventScop\\eventscop-frontend-guide\\src\\components\\common\\quote-sidebar\\ActivityQuoteForm.tsx",
            "fileType": ".tsx",
            "linesAdded": 0,
            "linesRemoved": 2,
            "projectName": "eventscop-frontend-guide (Workspace)",
            "content": {
              "added": [],
              "removed": []
            },
            "duration": 1,
            "language": "tsx"
          },
          {
            "timestamp": "2025-11-25T14:51:40.615Z",
            "fileName": "c:\\Mes Projets\\EventScop\\eventscop-frontend-guide\\src\\components\\common\\quote-sidebar\\ActivityQuoteForm.tsx",
            "fileType": ".tsx",
            "linesAdded": 1,
            "linesRemoved": 0,
            "projectName": "eventscop-frontend-guide (Workspace)",
            "content": {
              "added": [],
              "removed": []
            },
            "duration": 0,
            "language": "tsx"
          },
          {
            "timestamp": "2025-11-25T15:40:38.098Z",
            "fileName": "c:\\Mes Projets\\EventScop\\eventscop-frontend-guide\\src\\components\\common\\quote-sidebar\\ActivityQuoteForm.tsx",
            "fileType": ".tsx",
            "linesAdded": 0,
            "linesRemoved": 5,
            "projectName": "eventscop-frontend-guide (Workspace)",
            "content": {
              "added": [],
              "removed": []
            },
            "duration": 2,
            "language": "tsx"
          },
          {
            "timestamp": "2025-11-25T15:46:17.476Z",
            "fileName": "c:\\Mes Projets\\EventScop\\eventscop-frontend-guide\\src\\components\\common\\quote-sidebar\\ActivityQuoteForm.tsx",
            "fileType": ".tsx",
            "linesAdded": 5,
            "linesRemoved": 0,
            "projectName": "eventscop-frontend-guide (Workspace)",
            "content": {
              "added": [],
              "removed": []
            },
            "duration": 0,
            "language": "tsx"
          },
          {
            "timestamp": "2025-11-25T15:46:56.083Z",
            "fileName": "c:\\Mes Projets\\EventScop\\eventscop-frontend-guide\\src\\components\\common\\quote-sidebar\\ActivityQuoteForm.tsx",
            "fileType": ".tsx",
            "linesAdded": 7,
            "linesRemoved": 0,
            "projectName": "eventscop-frontend-guide (Workspace)",
            "content": {
              "added": [],
              "removed": []
            },
            "duration": 1,
            "language": "tsx"
          },
          {
            "timestamp": "2025-11-25T15:51:33.843Z",
            "fileName": "c:\\Mes Projets\\EventScop\\eventscop-frontend-guide\\src\\components\\common\\quote-sidebar\\ActivityQuoteForm.tsx",
            "fileType": ".tsx",
            "linesAdded": 2,
            "linesRemoved": 0,
            "projectName": "eventscop-frontend-guide (Workspace)",
            "content": {
              "added": [],
              "removed": []
            },
            "duration": 3,
            "language": "tsx"
          },
          {
            "timestamp": "2025-11-25T15:53:09.366Z",
            "fileName": "c:\\Mes Projets\\EventScop\\eventscop-frontend-guide\\src\\components\\common\\quote-sidebar\\ActivityQuoteForm.tsx",
            "fileType": ".tsx",
            "linesAdded": 0,
            "linesRemoved": 25,
            "projectName": "eventscop-frontend-guide (Workspace)",
            "content": {
              "added": [],
              "removed": []
            },
            "duration": 2,
            "language": "tsx"
          },
          {
            "timestamp": "2025-11-25T15:53:48.252Z",
            "fileName": "c:\\Mes Projets\\EventScop\\eventscop-frontend-guide\\src\\components\\common\\quote-sidebar\\ActivityQuoteForm.tsx",
            "fileType": ".tsx",
            "linesAdded": 25,
            "linesRemoved": 0,
            "projectName": "eventscop-frontend-guide (Workspace)",
            "content": {
              "added": [],
              "removed": []
            },
            "duration": 1,
            "language": "tsx"
          },
          {
            "timestamp": "2025-11-25T16:03:12.449Z",
            "fileName": "c:\\Mes Projets\\EventScop\\eventscop-frontend-guide\\src\\components\\common\\quote-sidebar\\ActivityQuoteForm.tsx",
            "fileType": ".tsx",
            "linesAdded": 0,
            "linesRemoved": 25,
            "projectName": "eventscop-frontend-guide (Workspace)",
            "content": {
              "added": [],
              "removed": []
            },
            "duration": 4,
            "language": "tsx"
          },
          {
            "timestamp": "2025-11-25T16:04:01.109Z",
            "fileName": "c:\\Mes Projets\\EventScop\\eventscop-frontend-guide\\src\\components\\common\\quote-sidebar\\ActivityQuoteForm.tsx",
            "fileType": ".tsx",
            "linesAdded": 25,
            "linesRemoved": 0,
            "projectName": "eventscop-frontend-guide (Workspace)",
            "content": {
              "added": [],
              "removed": []
            },
            "duration": 1,
            "language": "tsx"
          }
        ],
        "c:\\Mes Projets\\EventScop\\eventscop-frontend-guide\\src\\app\\[locale]\\(main)\\activity\\[[...url_path]]\\page.tsx": [
          {
            "timestamp": "2025-11-25T13:42:12.941Z",
            "fileName": "c:\\Mes Projets\\EventScop\\eventscop-frontend-guide\\src\\app\\[locale]\\(main)\\activity\\[[...url_path]]\\page.tsx",
            "fileType": ".tsx",
            "linesAdded": 149,
            "linesRemoved": 0,
            "projectName": "eventscop-frontend-guide (Workspace)",
            "content": {
              "added": [],
              "removed": []
            },
            "duration": 2,
            "language": "tsx"
          },
          {
            "timestamp": "2025-11-25T13:42:42.436Z",
            "fileName": "c:\\Mes Projets\\EventScop\\eventscop-frontend-guide\\src\\app\\[locale]\\(main)\\activity\\[[...url_path]]\\page.tsx",
            "fileType": ".tsx",
            "linesAdded": 1,
            "linesRemoved": 0,
            "projectName": "eventscop-frontend-guide (Workspace)",
            "content": {
              "added": [],
              "removed": []
            },
            "duration": 1,
            "language": "tsx"
          },
          {
            "timestamp": "2025-11-25T13:54:20.898Z",
            "fileName": "c:\\Mes Projets\\EventScop\\eventscop-frontend-guide\\src\\app\\[locale]\\(main)\\activity\\[[...url_path]]\\page.tsx",
            "fileType": ".tsx",
            "linesAdded": 2,
            "linesRemoved": 0,
            "projectName": "eventscop-frontend-guide (Workspace)",
            "content": {
              "added": [],
              "removed": []
            },
            "duration": 2,
            "language": "tsx"
          },
          {
            "timestamp": "2025-11-25T13:59:02.449Z",
            "fileName": "c:\\Mes Projets\\EventScop\\eventscop-frontend-guide\\src\\app\\[locale]\\(main)\\activity\\[[...url_path]]\\page.tsx",
            "fileType": ".tsx",
            "linesAdded": 2,
            "linesRemoved": 0,
            "projectName": "eventscop-frontend-guide (Workspace)",
            "content": {
              "added": [],
              "removed": []
            },
            "duration": 5,
            "language": "tsx"
          },
          {
            "timestamp": "2025-11-25T14:04:59.297Z",
            "fileName": "c:\\Mes Projets\\EventScop\\eventscop-frontend-guide\\src\\app\\[locale]\\(main)\\activity\\[[...url_path]]\\page.tsx",
            "fileType": ".tsx",
            "linesAdded": 16,
            "linesRemoved": 0,
            "projectName": "eventscop-frontend-guide (Workspace)",
            "content": {
              "added": [],
              "removed": []
            },
            "duration": 0,
            "language": "tsx"
          },
          {
            "timestamp": "2025-11-25T14:05:31.157Z",
            "fileName": "c:\\Mes Projets\\EventScop\\eventscop-frontend-guide\\src\\app\\[locale]\\(main)\\activity\\[[...url_path]]\\page.tsx",
            "fileType": ".tsx",
            "linesAdded": 0,
            "linesRemoved": 1,
            "projectName": "eventscop-frontend-guide (Workspace)",
            "content": {
              "added": [],
              "removed": []
            },
            "duration": 1,
            "language": "tsx"
          },
          {
            "timestamp": "2025-11-25T14:06:43.953Z",
            "fileName": "c:\\Mes Projets\\EventScop\\eventscop-frontend-guide\\src\\app\\[locale]\\(main)\\activity\\[[...url_path]]\\page.tsx",
            "fileType": ".tsx",
            "linesAdded": 1,
            "linesRemoved": 0,
            "projectName": "eventscop-frontend-guide (Workspace)",
            "content": {
              "added": [],
              "removed": []
            },
            "duration": 2,
            "language": "tsx"
          },
          {
            "timestamp": "2025-11-25T14:09:05.337Z",
            "fileName": "c:\\Mes Projets\\EventScop\\eventscop-frontend-guide\\src\\app\\[locale]\\(main)\\activity\\[[...url_path]]\\page.tsx",
            "fileType": ".tsx",
            "linesAdded": 0,
            "linesRemoved": 1,
            "projectName": "eventscop-frontend-guide (Workspace)",
            "content": {
              "added": [],
              "removed": []
            },
            "duration": 3,
            "language": "tsx"
          },
          {
            "timestamp": "2025-11-25T15:53:09.343Z",
            "fileName": "c:\\Mes Projets\\EventScop\\eventscop-frontend-guide\\src\\app\\[locale]\\(main)\\activity\\[[...url_path]]\\page.tsx",
            "fileType": ".tsx",
            "linesAdded": 0,
            "linesRemoved": 20,
            "projectName": "eventscop-frontend-guide (Workspace)",
            "content": {
              "added": [],
              "removed": []
            },
            "duration": 2,
            "language": "tsx"
          },
          {
            "timestamp": "2025-11-25T15:53:48.226Z",
            "fileName": "c:\\Mes Projets\\EventScop\\eventscop-frontend-guide\\src\\app\\[locale]\\(main)\\activity\\[[...url_path]]\\page.tsx",
            "fileType": ".tsx",
            "linesAdded": 20,
            "linesRemoved": 0,
            "projectName": "eventscop-frontend-guide (Workspace)",
            "content": {
              "added": [],
              "removed": []
            },
            "duration": 1,
            "language": "tsx"
          },
          {
            "timestamp": "2025-11-25T16:03:12.341Z",
            "fileName": "c:\\Mes Projets\\EventScop\\eventscop-frontend-guide\\src\\app\\[locale]\\(main)\\activity\\[[...url_path]]\\page.tsx",
            "fileType": ".tsx",
            "linesAdded": 0,
            "linesRemoved": 20,
            "projectName": "eventscop-frontend-guide (Workspace)",
            "content": {
              "added": [],
              "removed": []
            },
            "duration": 4,
            "language": "tsx"
          },
          {
            "timestamp": "2025-11-25T16:04:01.029Z",
            "fileName": "c:\\Mes Projets\\EventScop\\eventscop-frontend-guide\\src\\app\\[locale]\\(main)\\activity\\[[...url_path]]\\page.tsx",
            "fileType": ".tsx",
            "linesAdded": 20,
            "linesRemoved": 0,
            "projectName": "eventscop-frontend-guide (Workspace)",
            "content": {
              "added": [],
              "removed": []
            },
            "duration": 1,
            "language": "tsx"
          }
        ],
        "c:\\Mes Projets\\EventScop\\eventscop-frontend-guide\\src\\components\\activity\\ActivityQuoteSidebar.tsx": [
          {
            "timestamp": "2025-11-25T13:44:44.018Z",
            "fileName": "c:\\Mes Projets\\EventScop\\eventscop-frontend-guide\\src\\components\\activity\\ActivityQuoteSidebar.tsx",
            "fileType": ".tsx",
            "linesAdded": 31,
            "linesRemoved": 0,
            "projectName": "eventscop-frontend-guide (Workspace)",
            "content": {
              "added": [],
              "removed": []
            },
            "duration": 3,
            "language": "tsx"
          },
          {
            "timestamp": "2025-11-25T13:54:35.078Z",
            "fileName": "c:\\Mes Projets\\EventScop\\eventscop-frontend-guide\\src\\components\\activity\\ActivityQuoteSidebar.tsx",
            "fileType": ".tsx",
            "linesAdded": 1,
            "linesRemoved": 0,
            "projectName": "eventscop-frontend-guide (Workspace)",
            "content": {
              "added": [],
              "removed": []
            },
            "duration": 1,
            "language": "tsx"
          },
          {
            "timestamp": "2025-11-25T13:54:40.502Z",
            "fileName": "c:\\Mes Projets\\EventScop\\eventscop-frontend-guide\\src\\components\\activity\\ActivityQuoteSidebar.tsx",
            "fileType": ".tsx",
            "linesAdded": 0,
            "linesRemoved": 1,
            "projectName": "eventscop-frontend-guide (Workspace)",
            "content": {
              "added": [],
              "removed": []
            },
            "duration": 1,
            "language": "tsx"
          }
        ],
        "c:\\Mes Projets\\EventScop\\eventscop-frontend-guide\\src\\types\\common.ts": [
          {
            "timestamp": "2025-11-25T13:46:33.453Z",
            "fileName": "c:\\Mes Projets\\EventScop\\eventscop-frontend-guide\\src\\types\\common.ts",
            "fileType": ".ts",
            "linesAdded": 284,
            "linesRemoved": 0,
            "projectName": "eventscop-frontend-guide (Workspace)",
            "content": {
              "added": [],
              "removed": []
            },
            "duration": 2,
            "language": "ts"
          },
          {
            "timestamp": "2025-11-25T13:46:46.088Z",
            "fileName": "c:\\Mes Projets\\EventScop\\eventscop-frontend-guide\\src\\types\\common.ts",
            "fileType": ".ts",
            "linesAdded": 1,
            "linesRemoved": 0,
            "projectName": "eventscop-frontend-guide (Workspace)",
            "content": {
              "added": [],
              "removed": []
            },
            "duration": 1,
            "language": "ts"
          },
          {
            "timestamp": "2025-11-25T13:52:05.615Z",
            "fileName": "c:\\Mes Projets\\EventScop\\eventscop-frontend-guide\\src\\types\\common.ts",
            "fileType": ".ts",
            "linesAdded": 0,
            "linesRemoved": 1,
            "projectName": "eventscop-frontend-guide (Workspace)",
            "content": {
              "added": [],
              "removed": []
            },
            "duration": 1,
            "language": "ts"
          }
        ],
        "c:\\Mes Projets\\EventScop\\eventscop-frontend-guide\\src\\components\\common\\quote-sidebar\\QuoteTarifs.tsx": [
          {
            "timestamp": "2025-11-25T13:47:42.617Z",
            "fileName": "c:\\Mes Projets\\EventScop\\eventscop-frontend-guide\\src\\components\\common\\quote-sidebar\\QuoteTarifs.tsx",
            "fileType": ".tsx",
            "linesAdded": 44,
            "linesRemoved": 0,
            "projectName": "eventscop-frontend-guide (Workspace)",
            "content": {
              "added": [],
              "removed": []
            },
            "duration": 1,
            "language": "tsx"
          },
          {
            "timestamp": "2025-11-25T14:13:45.779Z",
            "fileName": "c:\\Mes Projets\\EventScop\\eventscop-frontend-guide\\src\\components\\common\\quote-sidebar\\QuoteTarifs.tsx",
            "fileType": ".tsx",
            "linesAdded": 17,
            "linesRemoved": 0,
            "projectName": "eventscop-frontend-guide (Workspace)",
            "content": {
              "added": [],
              "removed": []
            },
            "duration": 5,
            "language": "tsx"
          },
          {
            "timestamp": "2025-11-25T14:14:38.379Z",
            "fileName": "c:\\Mes Projets\\EventScop\\eventscop-frontend-guide\\src\\components\\common\\quote-sidebar\\QuoteTarifs.tsx",
            "fileType": ".tsx",
            "linesAdded": 2,
            "linesRemoved": 0,
            "projectName": "eventscop-frontend-guide (Workspace)",
            "content": {
              "added": [],
              "removed": []
            },
            "duration": 1,
            "language": "tsx"
          },
          {
            "timestamp": "2025-11-25T14:14:56.041Z",
            "fileName": "c:\\Mes Projets\\EventScop\\eventscop-frontend-guide\\src\\components\\common\\quote-sidebar\\QuoteTarifs.tsx",
            "fileType": ".tsx",
            "linesAdded": 0,
            "linesRemoved": 1,
            "projectName": "eventscop-frontend-guide (Workspace)",
            "content": {
              "added": [],
              "removed": []
            },
            "duration": 1,
            "language": "tsx"
          },
          {
            "timestamp": "2025-11-25T14:30:20.539Z",
            "fileName": "c:\\Mes Projets\\EventScop\\eventscop-frontend-guide\\src\\components\\common\\quote-sidebar\\QuoteTarifs.tsx",
            "fileType": ".tsx",
            "linesAdded": 1,
            "linesRemoved": 0,
            "projectName": "eventscop-frontend-guide (Workspace)",
            "content": {
              "added": [],
              "removed": []
            },
            "duration": 2,
            "language": "tsx"
          },
          {
            "timestamp": "2025-11-25T14:33:41.646Z",
            "fileName": "c:\\Mes Projets\\EventScop\\eventscop-frontend-guide\\src\\components\\common\\quote-sidebar\\QuoteTarifs.tsx",
            "fileType": ".tsx",
            "linesAdded": 1,
            "linesRemoved": 0,
            "projectName": "eventscop-frontend-guide (Workspace)",
            "content": {
              "added": [],
              "removed": []
            },
            "duration": 4,
            "language": "tsx"
          },
          {
            "timestamp": "2025-11-25T14:36:15.114Z",
            "fileName": "c:\\Mes Projets\\EventScop\\eventscop-frontend-guide\\src\\components\\common\\quote-sidebar\\QuoteTarifs.tsx",
            "fileType": ".tsx",
            "linesAdded": 4,
            "linesRemoved": 0,
            "projectName": "eventscop-frontend-guide (Workspace)",
            "content": {
              "added": [],
              "removed": []
            },
            "duration": 3,
            "language": "tsx"
          },
          {
            "timestamp": "2025-11-25T14:43:19.622Z",
            "fileName": "c:\\Mes Projets\\EventScop\\eventscop-frontend-guide\\src\\components\\common\\quote-sidebar\\QuoteTarifs.tsx",
            "fileType": ".tsx",
            "linesAdded": 23,
            "linesRemoved": 0,
            "projectName": "eventscop-frontend-guide (Workspace)",
            "content": {
              "added": [],
              "removed": []
            },
            "duration": 3,
            "language": "tsx"
          },
          {
            "timestamp": "2025-11-25T14:43:36.823Z",
            "fileName": "c:\\Mes Projets\\EventScop\\eventscop-frontend-guide\\src\\components\\common\\quote-sidebar\\QuoteTarifs.tsx",
            "fileType": ".tsx",
            "linesAdded": 0,
            "linesRemoved": 21,
            "projectName": "eventscop-frontend-guide (Workspace)",
            "content": {
              "added": [],
              "removed": []
            },
            "duration": 1,
            "language": "tsx"
          },
          {
            "timestamp": "2025-11-25T14:44:29.792Z",
            "fileName": "c:\\Mes Projets\\EventScop\\eventscop-frontend-guide\\src\\components\\common\\quote-sidebar\\QuoteTarifs.tsx",
            "fileType": ".tsx",
            "linesAdded": 1,
            "linesRemoved": 0,
            "projectName": "eventscop-frontend-guide (Workspace)",
            "content": {
              "added": [],
              "removed": []
            },
            "duration": 1,
            "language": "tsx"
          },
          {
            "timestamp": "2025-11-25T14:44:39.497Z",
            "fileName": "c:\\Mes Projets\\EventScop\\eventscop-frontend-guide\\src\\components\\common\\quote-sidebar\\QuoteTarifs.tsx",
            "fileType": ".tsx",
            "linesAdded": 2,
            "linesRemoved": 0,
            "projectName": "eventscop-frontend-guide (Workspace)",
            "content": {
              "added": [],
              "removed": []
            },
            "duration": 1,
            "language": "tsx"
          },
          {
            "timestamp": "2025-11-25T14:44:54.070Z",
            "fileName": "c:\\Mes Projets\\EventScop\\eventscop-frontend-guide\\src\\components\\common\\quote-sidebar\\QuoteTarifs.tsx",
            "fileType": ".tsx",
            "linesAdded": 22,
            "linesRemoved": 0,
            "projectName": "eventscop-frontend-guide (Workspace)",
            "content": {
              "added": [],
              "removed": []
            },
            "duration": 1,
            "language": "tsx"
          },
          {
            "timestamp": "2025-11-25T14:46:16.356Z",
            "fileName": "c:\\Mes Projets\\EventScop\\eventscop-frontend-guide\\src\\components\\common\\quote-sidebar\\QuoteTarifs.tsx",
            "fileType": ".tsx",
            "linesAdded": 0,
            "linesRemoved": 2,
            "projectName": "eventscop-frontend-guide (Workspace)",
            "content": {
              "added": [],
              "removed": []
            },
            "duration": 2,
            "language": "tsx"
          },
          {
            "timestamp": "2025-11-25T14:51:40.622Z",
            "fileName": "c:\\Mes Projets\\EventScop\\eventscop-frontend-guide\\src\\components\\common\\quote-sidebar\\QuoteTarifs.tsx",
            "fileType": ".tsx",
            "linesAdded": 6,
            "linesRemoved": 0,
            "projectName": "eventscop-frontend-guide (Workspace)",
            "content": {
              "added": [],
              "removed": []
            },
            "duration": 0,
            "language": "tsx"
          },
          {
            "timestamp": "2025-11-25T15:38:47.537Z",
            "fileName": "c:\\Mes Projets\\EventScop\\eventscop-frontend-guide\\src\\components\\common\\quote-sidebar\\QuoteTarifs.tsx",
            "fileType": ".tsx",
            "linesAdded": 0,
            "linesRemoved": 1,
            "projectName": "eventscop-frontend-guide (Workspace)",
            "content": {
              "added": [],
              "removed": []
            },
            "duration": 0,
            "language": "tsx"
          },
          {
            "timestamp": "2025-11-25T15:39:00.220Z",
            "fileName": "c:\\Mes Projets\\EventScop\\eventscop-frontend-guide\\src\\components\\common\\quote-sidebar\\QuoteTarifs.tsx",
            "fileType": ".tsx",
            "linesAdded": 0,
            "linesRemoved": 24,
            "projectName": "eventscop-frontend-guide (Workspace)",
            "content": {
              "added": [],
              "removed": []
            },
            "duration": 1,
            "language": "tsx"
          },
          {
            "timestamp": "2025-11-25T15:53:09.337Z",
            "fileName": "c:\\Mes Projets\\EventScop\\eventscop-frontend-guide\\src\\components\\common\\quote-sidebar\\QuoteTarifs.tsx",
            "fileType": ".tsx",
            "linesAdded": 0,
            "linesRemoved": 30,
            "projectName": "eventscop-frontend-guide (Workspace)",
            "content": {
              "added": [],
              "removed": []
            },
            "duration": 2,
            "language": "tsx"
          },
          {
            "timestamp": "2025-11-25T15:53:48.230Z",
            "fileName": "c:\\Mes Projets\\EventScop\\eventscop-frontend-guide\\src\\components\\common\\quote-sidebar\\QuoteTarifs.tsx",
            "fileType": ".tsx",
            "linesAdded": 30,
            "linesRemoved": 0,
            "projectName": "eventscop-frontend-guide (Workspace)",
            "content": {
              "added": [],
              "removed": []
            },
            "duration": 1,
            "language": "tsx"
          },
          {
            "timestamp": "2025-11-25T16:03:12.380Z",
            "fileName": "c:\\Mes Projets\\EventScop\\eventscop-frontend-guide\\src\\components\\common\\quote-sidebar\\QuoteTarifs.tsx",
            "fileType": ".tsx",
            "linesAdded": 0,
            "linesRemoved": 30,
            "projectName": "eventscop-frontend-guide (Workspace)",
            "content": {
              "added": [],
              "removed": []
            },
            "duration": 4,
            "language": "tsx"
          },
          {
            "timestamp": "2025-11-25T16:04:01.040Z",
            "fileName": "c:\\Mes Projets\\EventScop\\eventscop-frontend-guide\\src\\components\\common\\quote-sidebar\\QuoteTarifs.tsx",
            "fileType": ".tsx",
            "linesAdded": 30,
            "linesRemoved": 0,
            "projectName": "eventscop-frontend-guide (Workspace)",
            "content": {
              "added": [],
              "removed": []
            },
            "duration": 1,
            "language": "tsx"
          }
        ],
        "c:\\Mes Projets\\EventScop\\eventscop-frontend-guide\\src\\types\\product.ts": [
          {
            "timestamp": "2025-11-25T13:50:44.233Z",
            "fileName": "c:\\Mes Projets\\EventScop\\eventscop-frontend-guide\\src\\types\\product.ts",
            "fileType": ".ts",
            "linesAdded": 52,
            "linesRemoved": 0,
            "projectName": "eventscop-frontend-guide (Workspace)",
            "content": {
              "added": [],
              "removed": []
            },
            "duration": 4,
            "language": "ts"
          },
          {
            "timestamp": "2025-11-25T13:51:22.144Z",
            "fileName": "c:\\Mes Projets\\EventScop\\eventscop-frontend-guide\\src\\types\\product.ts",
            "fileType": ".ts",
            "linesAdded": 3,
            "linesRemoved": 0,
            "projectName": "eventscop-frontend-guide (Workspace)",
            "content": {
              "added": [],
              "removed": []
            },
            "duration": 1,
            "language": "ts"
          },
          {
            "timestamp": "2025-11-25T13:51:50.916Z",
            "fileName": "c:\\Mes Projets\\EventScop\\eventscop-frontend-guide\\src\\types\\product.ts",
            "fileType": ".ts",
            "linesAdded": 1,
            "linesRemoved": 0,
            "projectName": "eventscop-frontend-guide (Workspace)",
            "content": {
              "added": [],
              "removed": []
            },
            "duration": 1,
            "language": "ts"
          },
          {
            "timestamp": "2025-11-25T16:03:12.391Z",
            "fileName": "c:\\Mes Projets\\EventScop\\eventscop-frontend-guide\\src\\types\\product.ts",
            "fileType": ".ts",
            "linesAdded": 0,
            "linesRemoved": 4,
            "projectName": "eventscop-frontend-guide (Workspace)",
            "content": {
              "added": [],
              "removed": []
            },
            "duration": 4,
            "language": "ts"
          },
          {
            "timestamp": "2025-11-25T16:04:01.044Z",
            "fileName": "c:\\Mes Projets\\EventScop\\eventscop-frontend-guide\\src\\types\\product.ts",
            "fileType": ".ts",
            "linesAdded": 4,
            "linesRemoved": 0,
            "projectName": "eventscop-frontend-guide (Workspace)",
            "content": {
              "added": [],
              "removed": []
            },
            "duration": 1,
            "language": "ts"
          }
        ],
        "c:\\Mes Projets\\EventScop\\eventscop-frontend-guide\\src\\i18n\\locales\\fr.json": [
          {
            "timestamp": "2025-11-25T14:16:33.295Z",
            "fileName": "c:\\Mes Projets\\EventScop\\eventscop-frontend-guide\\src\\i18n\\locales\\fr.json",
            "fileType": ".json",
            "linesAdded": 1973,
            "linesRemoved": 0,
            "projectName": "eventscop-frontend-guide (Workspace)",
            "content": {
              "added": [],
              "removed": []
            },
            "duration": 2,
            "language": "json"
          },
          {
            "timestamp": "2025-11-25T14:16:44.424Z",
            "fileName": "c:\\Mes Projets\\EventScop\\eventscop-frontend-guide\\src\\i18n\\locales\\fr.json",
            "fileType": ".json",
            "linesAdded": 1,
            "linesRemoved": 0,
            "projectName": "eventscop-frontend-guide (Workspace)",
            "content": {
              "added": [],
              "removed": []
            },
            "duration": 1,
            "language": "json"
          },
          {
            "timestamp": "2025-11-25T15:53:09.355Z",
            "fileName": "c:\\Mes Projets\\EventScop\\eventscop-frontend-guide\\src\\i18n\\locales\\fr.json",
            "fileType": ".json",
            "linesAdded": 0,
            "linesRemoved": 1,
            "projectName": "eventscop-frontend-guide (Workspace)",
            "content": {
              "added": [],
              "removed": []
            },
            "duration": 2,
            "language": "json"
          },
          {
            "timestamp": "2025-11-25T15:53:48.247Z",
            "fileName": "c:\\Mes Projets\\EventScop\\eventscop-frontend-guide\\src\\i18n\\locales\\fr.json",
            "fileType": ".json",
            "linesAdded": 1,
            "linesRemoved": 0,
            "projectName": "eventscop-frontend-guide (Workspace)",
            "content": {
              "added": [],
              "removed": []
            },
            "duration": 1,
            "language": "json"
          },
          {
            "timestamp": "2025-11-25T16:03:12.437Z",
            "fileName": "c:\\Mes Projets\\EventScop\\eventscop-frontend-guide\\src\\i18n\\locales\\fr.json",
            "fileType": ".json",
            "linesAdded": 0,
            "linesRemoved": 1,
            "projectName": "eventscop-frontend-guide (Workspace)",
            "content": {
              "added": [],
              "removed": []
            },
            "duration": 4,
            "language": "json"
          },
          {
            "timestamp": "2025-11-25T16:04:01.069Z",
            "fileName": "c:\\Mes Projets\\EventScop\\eventscop-frontend-guide\\src\\i18n\\locales\\fr.json",
            "fileType": ".json",
            "linesAdded": 1,
            "linesRemoved": 0,
            "projectName": "eventscop-frontend-guide (Workspace)",
            "content": {
              "added": [],
              "removed": []
            },
            "duration": 1,
            "language": "json"
          }
        ],
        "c:\\Mes Projets\\EventScop\\eventscop-frontend-guide\\src\\app\\(sitemaps)\\sitemap-activities.xml\\route.ts": [
          {
            "timestamp": "2025-11-25T15:48:58.236Z",
            "fileName": "c:\\Mes Projets\\EventScop\\eventscop-frontend-guide\\src\\app\\(sitemaps)\\sitemap-activities.xml\\route.ts",
            "fileType": ".ts",
            "linesAdded": 73,
            "linesRemoved": 0,
            "projectName": "eventscop-frontend-guide (Workspace)",
            "content": {
              "added": [],
              "removed": []
            },
            "duration": 3,
            "language": "ts"
          }
        ],
        "c:\\Mes Projets\\EventScop\\eventscop-frontend-guide\\src\\lib\\utils\\place.ts": [
          {
            "timestamp": "2025-11-25T15:57:46.267Z",
            "fileName": "c:\\Mes Projets\\EventScop\\eventscop-frontend-guide\\src\\lib\\utils\\place.ts",
            "fileType": ".ts",
            "linesAdded": 18,
            "linesRemoved": 0,
            "projectName": "eventscop-frontend-guide (Workspace)",
            "content": {
              "added": [],
              "removed": []
            },
            "duration": 4,
            "language": "ts"
          },
          {
            "timestamp": "2025-11-25T15:57:52.675Z",
            "fileName": "c:\\Mes Projets\\EventScop\\eventscop-frontend-guide\\src\\lib\\utils\\place.ts",
            "fileType": ".ts",
            "linesAdded": 1,
            "linesRemoved": 0,
            "projectName": "eventscop-frontend-guide (Workspace)",
            "content": {
              "added": [],
              "removed": []
            },
            "duration": 1,
            "language": "ts"
          },
          {
            "timestamp": "2025-11-25T15:59:47.703Z",
            "fileName": "c:\\Mes Projets\\EventScop\\eventscop-frontend-guide\\src\\lib\\utils\\place.ts",
            "fileType": ".ts",
            "linesAdded": 0,
            "linesRemoved": 1,
            "projectName": "eventscop-frontend-guide (Workspace)",
            "content": {
              "added": [],
              "removed": []
            },
            "duration": 2,
            "language": "ts"
          },
          {
            "timestamp": "2025-11-25T15:59:52.400Z",
            "fileName": "c:\\Mes Projets\\EventScop\\eventscop-frontend-guide\\src\\lib\\utils\\place.ts",
            "fileType": ".ts",
            "linesAdded": 1,
            "linesRemoved": 0,
            "projectName": "eventscop-frontend-guide (Workspace)",
            "content": {
              "added": [],
              "removed": []
            },
            "duration": 1,
            "language": "ts"
          },
          {
            "timestamp": "2025-11-25T16:03:12.385Z",
            "fileName": "c:\\Mes Projets\\EventScop\\eventscop-frontend-guide\\src\\lib\\utils\\place.ts",
            "fileType": ".ts",
            "linesAdded": 0,
            "linesRemoved": 1,
            "projectName": "eventscop-frontend-guide (Workspace)",
            "content": {
              "added": [],
              "removed": []
            },
            "duration": 4,
            "language": "ts"
          },
          {
            "timestamp": "2025-11-25T16:04:01.048Z",
            "fileName": "c:\\Mes Projets\\EventScop\\eventscop-frontend-guide\\src\\lib\\utils\\place.ts",
            "fileType": ".ts",
            "linesAdded": 1,
            "linesRemoved": 0,
            "projectName": "eventscop-frontend-guide (Workspace)",
            "content": {
              "added": [],
              "removed": []
            },
            "duration": 1,
            "language": "ts"
          }
        ]
      },
      "languageStats": {
        "json": 1
      },
      "changeFrequency": {
        "9": 1
      },
      "topFiles": [
        "c:\\Mes Projets\\EventScop\\eventscop-frontend-guide\\.next\\package.json"
      ],
      "averageChangeSize": 2.5
    },
    "cdp.aleoudev.fr (Workspace)": {
      "totalLinesAdded": 1618,
      "totalLinesRemoved": 0,
      "totalActiveTime": 0,
      "files": {
        "c:\\Mes Projets\\www\\iis\\cdp.aleoudev.fr\\xdev\\api\\synchro-eventscop\\modules\\etab_queries\\functions.asp": [
          {
            "timestamp": "2025-11-25T15:28:12.871Z",
            "fileName": "c:\\Mes Projets\\www\\iis\\cdp.aleoudev.fr\\xdev\\api\\synchro-eventscop\\modules\\etab_queries\\functions.asp",
            "fileType": ".asp",
            "linesAdded": 1618,
            "linesRemoved": 0,
            "projectName": "cdp.aleoudev.fr (Workspace)",
            "content": {
              "added": [],
              "removed": []
            },
            "duration": 0,
            "language": "asp"
          }
        ]
      },
      "languageStats": {
        "asp": 0
      },
      "changeFrequency": {
        "16": 0
      },
      "topFiles": [
        "c:\\Mes Projets\\www\\iis\\cdp.aleoudev.fr\\xdev\\api\\synchro-eventscop\\modules\\etab_queries\\functions.asp"
      ],
      "averageChangeSize": 1618
    }
  },
  "totalActiveTime": 6,
  "totalProjects": 1,
  "totalFiles": 3,
  "mostActiveHours": [
    0
  ],
  "mostUsedLanguages": [
    "py"
  ]
}