{
  "date": "2025-11-28",
  "projects": {
    "cdp.aleoudev.fr (Workspace)": {
      "totalLinesAdded": 15850,
      "totalLinesRemoved": 188,
      "totalActiveTime": 51,
      "files": {
        "c:\\Mes Projets\\www\\iis\\cdp.aleoudev.fr\\xdev\\cdp\\usr\\dev\\parts\\demandes\\demande_step_0.asp": [
          {
            "timestamp": "2025-11-27T23:01:12.464Z",
            "fileName": "c:\\Mes Projets\\www\\iis\\cdp.aleoudev.fr\\xdev\\cdp\\usr\\dev\\parts\\demandes\\demande_step_0.asp",
            "fileType": ".asp",
            "linesAdded": 96,
            "linesRemoved": 0,
            "projectName": "cdp.aleoudev.fr (Workspace)",
            "content": {
              "added": [],
              "removed": []
            },
            "duration": 0,
            "language": "asp"
          },
          {
            "timestamp": "2025-11-27T23:31:32.005Z",
            "fileName": "c:\\Mes Projets\\www\\iis\\cdp.aleoudev.fr\\xdev\\cdp\\usr\\dev\\parts\\demandes\\demande_step_0.asp",
            "fileType": ".asp",
            "linesAdded": 0,
            "linesRemoved": 5,
            "projectName": "cdp.aleoudev.fr (Workspace)",
            "content": {
              "added": [],
              "removed": []
            },
            "duration": 0,
            "language": "asp"
          },
          {
            "timestamp": "2025-11-28T00:48:50.702Z",
            "fileName": "c:\\Mes Projets\\www\\iis\\cdp.aleoudev.fr\\xdev\\cdp\\usr\\dev\\parts\\demandes\\demande_step_0.asp",
            "fileType": ".asp",
            "linesAdded": 3162,
            "linesRemoved": 0,
            "projectName": "cdp.aleoudev.fr (Workspace)",
            "content": {
              "added": [],
              "removed": []
            },
            "duration": 0,
            "language": "asp"
          },
          {
            "timestamp": "2025-11-28T10:57:35.703Z",
            "fileName": "c:\\Mes Projets\\www\\iis\\cdp.aleoudev.fr\\xdev\\cdp\\usr\\dev\\parts\\demandes\\demande_step_0.asp",
            "fileType": ".asp",
            "linesAdded": 1,
            "linesRemoved": 0,
            "projectName": "cdp.aleoudev.fr (Workspace)",
            "content": {
              "added": [],
              "removed": []
            },
            "duration": 0,
            "language": "asp"
          },
          {
            "timestamp": "2025-11-28T11:01:31.566Z",
            "fileName": "c:\\Mes Projets\\www\\iis\\cdp.aleoudev.fr\\xdev\\cdp\\usr\\dev\\parts\\demandes\\demande_step_0.asp",
            "fileType": ".asp",
            "linesAdded": 0,
            "linesRemoved": 1,
            "projectName": "cdp.aleoudev.fr (Workspace)",
            "content": {
              "added": [],
              "removed": []
            },
            "duration": 4,
            "language": "asp"
          },
          {
            "timestamp": "2025-11-28T11:05:07.143Z",
            "fileName": "c:\\Mes Projets\\www\\iis\\cdp.aleoudev.fr\\xdev\\cdp\\usr\\dev\\parts\\demandes\\demande_step_0.asp",
            "fileType": ".asp",
            "linesAdded": 0,
            "linesRemoved": 1,
            "projectName": "cdp.aleoudev.fr (Workspace)",
            "content": {
              "added": [],
              "removed": []
            },
            "duration": 4,
            "language": "asp"
          },
          {
            "timestamp": "2025-11-28T11:31:21.089Z",
            "fileName": "c:\\Mes Projets\\www\\iis\\cdp.aleoudev.fr\\xdev\\cdp\\usr\\dev\\parts\\demandes\\demande_step_0.asp",
            "fileType": ".asp",
            "linesAdded": 7,
            "linesRemoved": 0,
            "projectName": "cdp.aleoudev.fr (Workspace)",
            "content": {
              "added": [],
              "removed": []
            },
            "duration": 0,
            "language": "asp"
          },
          {
            "timestamp": "2025-11-28T13:10:16.352Z",
            "fileName": "c:\\Mes Projets\\www\\iis\\cdp.aleoudev.fr\\xdev\\cdp\\usr\\dev\\parts\\demandes\\demande_step_0.asp",
            "fileType": ".asp",
            "linesAdded": 0,
            "linesRemoved": 1,
            "projectName": "cdp.aleoudev.fr (Workspace)",
            "content": {
              "added": [],
              "removed": []
            },
            "duration": 0,
            "language": "asp"
          }
        ],
        "c:\\Mes Projets\\www\\iis\\cdp.aleoudev.fr\\xdev\\api\\synchro-eventscop\\modules\\etab_queries\\functions.asp": [
          {
            "timestamp": "2025-11-27T23:09:00.914Z",
            "fileName": "c:\\Mes Projets\\www\\iis\\cdp.aleoudev.fr\\xdev\\api\\synchro-eventscop\\modules\\etab_queries\\functions.asp",
            "fileType": ".asp",
            "linesAdded": 0,
            "linesRemoved": 1,
            "projectName": "cdp.aleoudev.fr (Workspace)",
            "content": {
              "added": [],
              "removed": []
            },
            "duration": 0,
            "language": "asp"
          },
          {
            "timestamp": "2025-11-27T23:10:17.552Z",
            "fileName": "c:\\Mes Projets\\www\\iis\\cdp.aleoudev.fr\\xdev\\api\\synchro-eventscop\\modules\\etab_queries\\functions.asp",
            "fileType": ".asp",
            "linesAdded": 1,
            "linesRemoved": 0,
            "projectName": "cdp.aleoudev.fr (Workspace)",
            "content": {
              "added": [],
              "removed": []
            },
            "duration": 2,
            "language": "asp"
          },
          {
            "timestamp": "2025-11-27T23:14:57.568Z",
            "fileName": "c:\\Mes Projets\\www\\iis\\cdp.aleoudev.fr\\xdev\\api\\synchro-eventscop\\modules\\etab_queries\\functions.asp",
            "fileType": ".asp",
            "linesAdded": 2,
            "linesRemoved": 0,
            "projectName": "cdp.aleoudev.fr (Workspace)",
            "content": {
              "added": [],
              "removed": []
            },
            "duration": 5,
            "language": "asp"
          },
          {
            "timestamp": "2025-11-27T23:19:53.804Z",
            "fileName": "c:\\Mes Projets\\www\\iis\\cdp.aleoudev.fr\\xdev\\api\\synchro-eventscop\\modules\\etab_queries\\functions.asp",
            "fileType": ".asp",
            "linesAdded": 8,
            "linesRemoved": 0,
            "projectName": "cdp.aleoudev.fr (Workspace)",
            "content": {
              "added": [],
              "removed": []
            },
            "duration": 5,
            "language": "asp"
          },
          {
            "timestamp": "2025-11-27T23:20:07.530Z",
            "fileName": "c:\\Mes Projets\\www\\iis\\cdp.aleoudev.fr\\xdev\\api\\synchro-eventscop\\modules\\etab_queries\\functions.asp",
            "fileType": ".asp",
            "linesAdded": 0,
            "linesRemoved": 1,
            "projectName": "cdp.aleoudev.fr (Workspace)",
            "content": {
              "added": [],
              "removed": []
            },
            "duration": 1,
            "language": "asp"
          },
          {
            "timestamp": "2025-11-27T23:20:12.190Z",
            "fileName": "c:\\Mes Projets\\www\\iis\\cdp.aleoudev.fr\\xdev\\api\\synchro-eventscop\\modules\\etab_queries\\functions.asp",
            "fileType": ".asp",
            "linesAdded": 0,
            "linesRemoved": 1,
            "projectName": "cdp.aleoudev.fr (Workspace)",
            "content": {
              "added": [],
              "removed": []
            },
            "duration": 1,
            "language": "asp"
          },
          {
            "timestamp": "2025-11-27T23:23:17.996Z",
            "fileName": "c:\\Mes Projets\\www\\iis\\cdp.aleoudev.fr\\xdev\\api\\synchro-eventscop\\modules\\etab_queries\\functions.asp",
            "fileType": ".asp",
            "linesAdded": 13,
            "linesRemoved": 0,
            "projectName": "cdp.aleoudev.fr (Workspace)",
            "content": {
              "added": [],
              "removed": []
            },
            "duration": 4,
            "language": "asp"
          },
          {
            "timestamp": "2025-11-27T23:24:36.746Z",
            "fileName": "c:\\Mes Projets\\www\\iis\\cdp.aleoudev.fr\\xdev\\api\\synchro-eventscop\\modules\\etab_queries\\functions.asp",
            "fileType": ".asp",
            "linesAdded": 5,
            "linesRemoved": 0,
            "projectName": "cdp.aleoudev.fr (Workspace)",
            "content": {
              "added": [],
              "removed": []
            },
            "duration": 2,
            "language": "asp"
          },
          {
            "timestamp": "2025-11-27T23:35:26.007Z",
            "fileName": "c:\\Mes Projets\\www\\iis\\cdp.aleoudev.fr\\xdev\\api\\synchro-eventscop\\modules\\etab_queries\\functions.asp",
            "fileType": ".asp",
            "linesAdded": 0,
            "linesRemoved": 2,
            "projectName": "cdp.aleoudev.fr (Workspace)",
            "content": {
              "added": [],
              "removed": []
            },
            "duration": 4,
            "language": "asp"
          },
          {
            "timestamp": "2025-11-28T00:33:30.441Z",
            "fileName": "c:\\Mes Projets\\www\\iis\\cdp.aleoudev.fr\\xdev\\api\\synchro-eventscop\\modules\\etab_queries\\functions.asp",
            "fileType": ".asp",
            "linesAdded": 1729,
            "linesRemoved": 0,
            "projectName": "cdp.aleoudev.fr (Workspace)",
            "content": {
              "added": [],
              "removed": []
            },
            "duration": 0,
            "language": "asp"
          },
          {
            "timestamp": "2025-11-28T09:19:52.899Z",
            "fileName": "c:\\Mes Projets\\www\\iis\\cdp.aleoudev.fr\\xdev\\api\\synchro-eventscop\\modules\\etab_queries\\functions.asp",
            "fileType": ".asp",
            "linesAdded": 0,
            "linesRemoved": 1,
            "projectName": "cdp.aleoudev.fr (Workspace)",
            "content": {
              "added": [],
              "removed": []
            },
            "duration": 0,
            "language": "asp"
          },
          {
            "timestamp": "2025-11-28T11:40:06.237Z",
            "fileName": "c:\\Mes Projets\\www\\iis\\cdp.aleoudev.fr\\xdev\\api\\synchro-eventscop\\modules\\etab_queries\\functions.asp",
            "fileType": ".asp",
            "linesAdded": 0,
            "linesRemoved": 1,
            "projectName": "cdp.aleoudev.fr (Workspace)",
            "content": {
              "added": [],
              "removed": []
            },
            "duration": 0,
            "language": "asp"
          },
          {
            "timestamp": "2025-11-28T12:11:29.024Z",
            "fileName": "c:\\Mes Projets\\www\\iis\\cdp.aleoudev.fr\\xdev\\api\\synchro-eventscop\\modules\\etab_queries\\functions.asp",
            "fileType": ".asp",
            "linesAdded": 34,
            "linesRemoved": 0,
            "projectName": "cdp.aleoudev.fr (Workspace)",
            "content": {
              "added": [],
              "removed": []
            },
            "duration": 0,
            "language": "asp"
          },
          {
            "timestamp": "2025-11-28T12:11:30.809Z",
            "fileName": "c:\\Mes Projets\\www\\iis\\cdp.aleoudev.fr\\xdev\\api\\synchro-eventscop\\modules\\etab_queries\\functions.asp",
            "fileType": ".asp",
            "linesAdded": 0,
            "linesRemoved": 2,
            "projectName": "cdp.aleoudev.fr (Workspace)",
            "content": {
              "added": [],
              "removed": []
            },
            "duration": 1,
            "language": "asp"
          },
          {
            "timestamp": "2025-11-28T12:21:25.210Z",
            "fileName": "c:\\Mes Projets\\www\\iis\\cdp.aleoudev.fr\\xdev\\api\\synchro-eventscop\\modules\\etab_queries\\functions.asp",
            "fileType": ".asp",
            "linesAdded": 1,
            "linesRemoved": 0,
            "projectName": "cdp.aleoudev.fr (Workspace)",
            "content": {
              "added": [],
              "removed": []
            },
            "duration": 0,
            "language": "asp"
          },
          {
            "timestamp": "2025-11-28T12:22:04.151Z",
            "fileName": "c:\\Mes Projets\\www\\iis\\cdp.aleoudev.fr\\xdev\\api\\synchro-eventscop\\modules\\etab_queries\\functions.asp",
            "fileType": ".asp",
            "linesAdded": 0,
            "linesRemoved": 7,
            "projectName": "cdp.aleoudev.fr (Workspace)",
            "content": {
              "added": [],
              "removed": []
            },
            "duration": 1,
            "language": "asp"
          },
          {
            "timestamp": "2025-11-28T12:27:46.899Z",
            "fileName": "c:\\Mes Projets\\www\\iis\\cdp.aleoudev.fr\\xdev\\api\\synchro-eventscop\\modules\\etab_queries\\functions.asp",
            "fileType": ".asp",
            "linesAdded": 0,
            "linesRemoved": 17,
            "projectName": "cdp.aleoudev.fr (Workspace)",
            "content": {
              "added": [],
              "removed": []
            },
            "duration": 0,
            "language": "asp"
          },
          {
            "timestamp": "2025-11-28T12:28:03.730Z",
            "fileName": "c:\\Mes Projets\\www\\iis\\cdp.aleoudev.fr\\xdev\\api\\synchro-eventscop\\modules\\etab_queries\\functions.asp",
            "fileType": ".asp",
            "linesAdded": 0,
            "linesRemoved": 1,
            "projectName": "cdp.aleoudev.fr (Workspace)",
            "content": {
              "added": [],
              "removed": []
            },
            "duration": 1,
            "language": "asp"
          },
          {
            "timestamp": "2025-11-28T15:34:21.509Z",
            "fileName": "c:\\Mes Projets\\www\\iis\\cdp.aleoudev.fr\\xdev\\api\\synchro-eventscop\\modules\\etab_queries\\functions.asp",
            "fileType": ".asp",
            "linesAdded": 1735,
            "linesRemoved": 0,
            "projectName": "cdp.aleoudev.fr (Workspace)",
            "content": {
              "added": [],
              "removed": []
            },
            "duration": 0,
            "language": "asp"
          },
          {
            "timestamp": "2025-11-28T15:35:24.952Z",
            "fileName": "c:\\Mes Projets\\www\\iis\\cdp.aleoudev.fr\\xdev\\api\\synchro-eventscop\\modules\\etab_queries\\functions.asp",
            "fileType": ".asp",
            "linesAdded": 0,
            "linesRemoved": 1,
            "projectName": "cdp.aleoudev.fr (Workspace)",
            "content": {
              "added": [],
              "removed": []
            },
            "duration": 2,
            "language": "asp"
          },
          {
            "timestamp": "2025-11-28T15:43:42.597Z",
            "fileName": "c:\\Mes Projets\\www\\iis\\cdp.aleoudev.fr\\xdev\\api\\synchro-eventscop\\modules\\etab_queries\\functions.asp",
            "fileType": ".asp",
            "linesAdded": 3,
            "linesRemoved": 0,
            "projectName": "cdp.aleoudev.fr (Workspace)",
            "content": {
              "added": [],
              "removed": []
            },
            "duration": 0,
            "language": "asp"
          }
        ],
        "c:\\Mes Projets\\www\\iis\\cdp.aleoudev.fr\\xdev\\api\\synchro-eventscop\\dashboard.asp": [
          {
            "timestamp": "2025-11-28T00:39:53.616Z",
            "fileName": "c:\\Mes Projets\\www\\iis\\cdp.aleoudev.fr\\xdev\\api\\synchro-eventscop\\dashboard.asp",
            "fileType": ".asp",
            "linesAdded": 1150,
            "linesRemoved": 0,
            "projectName": "cdp.aleoudev.fr (Workspace)",
            "content": {
              "added": [],
              "removed": []
            },
            "duration": 0,
            "language": "asp"
          },
          {
            "timestamp": "2025-11-28T00:40:55.338Z",
            "fileName": "c:\\Mes Projets\\www\\iis\\cdp.aleoudev.fr\\xdev\\api\\synchro-eventscop\\dashboard.asp",
            "fileType": ".asp",
            "linesAdded": 4,
            "linesRemoved": 0,
            "projectName": "cdp.aleoudev.fr (Workspace)",
            "content": {
              "added": [],
              "removed": []
            },
            "duration": 2,
            "language": "asp"
          }
        ],
        "c:\\Mes Projets\\www\\iis\\cdp.aleoudev.fr\\xdev\\cdp\\usr\\dev\\parts\\demandes\\demande_action_db.asp": [
          {
            "timestamp": "2025-11-28T11:32:02.352Z",
            "fileName": "c:\\Mes Projets\\www\\iis\\cdp.aleoudev.fr\\xdev\\cdp\\usr\\dev\\parts\\demandes\\demande_action_db.asp",
            "fileType": ".asp",
            "linesAdded": 2014,
            "linesRemoved": 0,
            "projectName": "cdp.aleoudev.fr (Workspace)",
            "content": {
              "added": [],
              "removed": []
            },
            "duration": 1,
            "language": "asp"
          },
          {
            "timestamp": "2025-11-28T11:32:07.757Z",
            "fileName": "c:\\Mes Projets\\www\\iis\\cdp.aleoudev.fr\\xdev\\cdp\\usr\\dev\\parts\\demandes\\demande_action_db.asp",
            "fileType": ".asp",
            "linesAdded": 1,
            "linesRemoved": 0,
            "projectName": "cdp.aleoudev.fr (Workspace)",
            "content": {
              "added": [],
              "removed": []
            },
            "duration": 1,
            "language": "asp"
          }
        ],
        "c:\\Mes Projets\\www\\iis\\cdp.aleoudev.fr\\xdev\\scripts\\outils.asp": [
          {
            "timestamp": "2025-11-28T11:41:20.854Z",
            "fileName": "c:\\Mes Projets\\www\\iis\\cdp.aleoudev.fr\\xdev\\scripts\\outils.asp",
            "fileType": ".asp",
            "linesAdded": 4030,
            "linesRemoved": 0,
            "projectName": "cdp.aleoudev.fr (Workspace)",
            "content": {
              "added": [],
              "removed": []
            },
            "duration": 2,
            "language": "asp"
          },
          {
            "timestamp": "2025-11-28T11:43:52.500Z",
            "fileName": "c:\\Mes Projets\\www\\iis\\cdp.aleoudev.fr\\xdev\\scripts\\outils.asp",
            "fileType": ".asp",
            "linesAdded": 143,
            "linesRemoved": 0,
            "projectName": "cdp.aleoudev.fr (Workspace)",
            "content": {
              "added": [],
              "removed": []
            },
            "duration": 3,
            "language": "asp"
          },
          {
            "timestamp": "2025-11-28T11:48:48.656Z",
            "fileName": "c:\\Mes Projets\\www\\iis\\cdp.aleoudev.fr\\xdev\\scripts\\outils.asp",
            "fileType": ".asp",
            "linesAdded": 0,
            "linesRemoved": 145,
            "projectName": "cdp.aleoudev.fr (Workspace)",
            "content": {
              "added": [],
              "removed": []
            },
            "duration": 5,
            "language": "asp"
          }
        ],
        "c:\\Mes Projets\\www\\iis\\cdp.aleoudev.fr\\xdev\\cdp\\usr\\dev\\parts\\demandes\\demande_step_5_tab_presta.asp": [
          {
            "timestamp": "2025-11-28T15:08:09.700Z",
            "fileName": "c:\\Mes Projets\\www\\iis\\cdp.aleoudev.fr\\xdev\\cdp\\usr\\dev\\parts\\demandes\\demande_step_5_tab_presta.asp",
            "fileType": ".asp",
            "linesAdded": 1711,
            "linesRemoved": 0,
            "projectName": "cdp.aleoudev.fr (Workspace)",
            "content": {
              "added": [],
              "removed": []
            },
            "duration": 0,
            "language": "asp"
          }
        ]
      },
      "languageStats": {
        "asp": 0
      },
      "changeFrequency": {
        "0": 0
      },
      "topFiles": [
        "c:\\Mes Projets\\www\\iis\\cdp.aleoudev.fr\\xdev\\cdp\\usr\\dev\\parts\\demandes\\demande_step_0.asp"
      ],
      "averageChangeSize": 96
    },
    "frontend-cms": {
      "totalLinesAdded": 1,
      "totalLinesRemoved": 0,
      "totalActiveTime": 0,
      "files": {
        "c:\\Mes Projets\\EventScop\\frontend-cms\\src\\lib\\api\\auth.ts": [
          {
            "timestamp": "2025-11-27T23:46:40.149Z",
            "fileName": "c:\\Mes Projets\\EventScop\\frontend-cms\\src\\lib\\api\\auth.ts",
            "fileType": ".ts",
            "linesAdded": 1,
            "linesRemoved": 0,
            "projectName": "frontend-cms",
            "content": {
              "added": [],
              "removed": []
            },
            "duration": 0,
            "language": "ts"
          }
        ]
      },
      "languageStats": {
        "ts": 0
      },
      "changeFrequency": {
        "0": 0
      },
      "topFiles": [
        "c:\\Mes Projets\\EventScop\\frontend-cms\\src\\lib\\api\\auth.ts"
      ],
      "averageChangeSize": 1
    },
    "eventscop-frontend-guide (Workspace)": {
      "totalLinesAdded": 3135,
      "totalLinesRemoved": 132,
      "totalActiveTime": 51,
      "files": {
        "c:\\Mes Projets\\EventScop\\eventscop-frontend-guide\\src\\components\\brief\\steps\\RecapConfirmation.tsx": [
          {
            "timestamp": "2025-11-28T01:58:20.493Z",
            "fileName": "c:\\Mes Projets\\EventScop\\eventscop-frontend-guide\\src\\components\\brief\\steps\\RecapConfirmation.tsx",
            "fileType": ".tsx",
            "linesAdded": 64,
            "linesRemoved": 0,
            "projectName": "eventscop-frontend-guide (Workspace)",
            "content": {
              "added": [],
              "removed": []
            },
            "duration": 0,
            "language": "tsx"
          },
          {
            "timestamp": "2025-11-28T01:59:58.189Z",
            "fileName": "c:\\Mes Projets\\EventScop\\eventscop-frontend-guide\\src\\components\\brief\\steps\\RecapConfirmation.tsx",
            "fileType": ".tsx",
            "linesAdded": 0,
            "linesRemoved": 1,
            "projectName": "eventscop-frontend-guide (Workspace)",
            "content": {
              "added": [],
              "removed": []
            },
            "duration": 2,
            "language": "tsx"
          },
          {
            "timestamp": "2025-11-28T02:00:13.399Z",
            "fileName": "c:\\Mes Projets\\EventScop\\eventscop-frontend-guide\\src\\components\\brief\\steps\\RecapConfirmation.tsx",
            "fileType": ".tsx",
            "linesAdded": 0,
            "linesRemoved": 4,
            "projectName": "eventscop-frontend-guide (Workspace)",
            "content": {
              "added": [],
              "removed": []
            },
            "duration": 1,
            "language": "tsx"
          },
          {
            "timestamp": "2025-11-28T02:00:35.437Z",
            "fileName": "c:\\Mes Projets\\EventScop\\eventscop-frontend-guide\\src\\components\\brief\\steps\\RecapConfirmation.tsx",
            "fileType": ".tsx",
            "linesAdded": 5,
            "linesRemoved": 0,
            "projectName": "eventscop-frontend-guide (Workspace)",
            "content": {
              "added": [],
              "removed": []
            },
            "duration": 1,
            "language": "tsx"
          }
        ],
        "c:\\Mes Projets\\EventScop\\eventscop-frontend-guide\\src\\components\\Footer.tsx": [
          {
            "timestamp": "2025-11-28T02:04:15.662Z",
            "fileName": "c:\\Mes Projets\\EventScop\\eventscop-frontend-guide\\src\\components\\Footer.tsx",
            "fileType": ".tsx",
            "linesAdded": 83,
            "linesRemoved": 0,
            "projectName": "eventscop-frontend-guide (Workspace)",
            "content": {
              "added": [],
              "removed": []
            },
            "duration": 4,
            "language": "tsx"
          },
          {
            "timestamp": "2025-11-28T02:06:10.401Z",
            "fileName": "c:\\Mes Projets\\EventScop\\eventscop-frontend-guide\\src\\components\\Footer.tsx",
            "fileType": ".tsx",
            "linesAdded": 37,
            "linesRemoved": 0,
            "projectName": "eventscop-frontend-guide (Workspace)",
            "content": {
              "added": [],
              "removed": []
            },
            "duration": 2,
            "language": "tsx"
          },
          {
            "timestamp": "2025-11-28T02:06:44.479Z",
            "fileName": "c:\\Mes Projets\\EventScop\\eventscop-frontend-guide\\src\\components\\Footer.tsx",
            "fileType": ".tsx",
            "linesAdded": 1,
            "linesRemoved": 0,
            "projectName": "eventscop-frontend-guide (Workspace)",
            "content": {
              "added": [],
              "removed": []
            },
            "duration": 1,
            "language": "tsx"
          },
          {
            "timestamp": "2025-11-28T02:08:04.342Z",
            "fileName": "c:\\Mes Projets\\EventScop\\eventscop-frontend-guide\\src\\components\\Footer.tsx",
            "fileType": ".tsx",
            "linesAdded": 1,
            "linesRemoved": 0,
            "projectName": "eventscop-frontend-guide (Workspace)",
            "content": {
              "added": [],
              "removed": []
            },
            "duration": 2,
            "language": "tsx"
          },
          {
            "timestamp": "2025-11-28T02:08:16.747Z",
            "fileName": "c:\\Mes Projets\\EventScop\\eventscop-frontend-guide\\src\\components\\Footer.tsx",
            "fileType": ".tsx",
            "linesAdded": 0,
            "linesRemoved": 39,
            "projectName": "eventscop-frontend-guide (Workspace)",
            "content": {
              "added": [],
              "removed": []
            },
            "duration": 1,
            "language": "tsx"
          },
          {
            "timestamp": "2025-11-28T02:08:42.874Z",
            "fileName": "c:\\Mes Projets\\EventScop\\eventscop-frontend-guide\\src\\components\\Footer.tsx",
            "fileType": ".tsx",
            "linesAdded": 39,
            "linesRemoved": 0,
            "projectName": "eventscop-frontend-guide (Workspace)",
            "content": {
              "added": [],
              "removed": []
            },
            "duration": 1,
            "language": "tsx"
          },
          {
            "timestamp": "2025-11-28T02:12:36.389Z",
            "fileName": "c:\\Mes Projets\\EventScop\\eventscop-frontend-guide\\src\\components\\Footer.tsx",
            "fileType": ".tsx",
            "linesAdded": 1,
            "linesRemoved": 0,
            "projectName": "eventscop-frontend-guide (Workspace)",
            "content": {
              "added": [],
              "removed": []
            },
            "duration": 4,
            "language": "tsx"
          },
          {
            "timestamp": "2025-11-28T02:13:00.456Z",
            "fileName": "c:\\Mes Projets\\EventScop\\eventscop-frontend-guide\\src\\components\\Footer.tsx",
            "fileType": ".tsx",
            "linesAdded": 16,
            "linesRemoved": 0,
            "projectName": "eventscop-frontend-guide (Workspace)",
            "content": {
              "added": [],
              "removed": []
            },
            "duration": 1,
            "language": "tsx"
          },
          {
            "timestamp": "2025-11-28T02:14:01.911Z",
            "fileName": "c:\\Mes Projets\\EventScop\\eventscop-frontend-guide\\src\\components\\Footer.tsx",
            "fileType": ".tsx",
            "linesAdded": 13,
            "linesRemoved": 0,
            "projectName": "eventscop-frontend-guide (Workspace)",
            "content": {
              "added": [],
              "removed": []
            },
            "duration": 2,
            "language": "tsx"
          },
          {
            "timestamp": "2025-11-28T02:56:49.817Z",
            "fileName": "c:\\Mes Projets\\EventScop\\eventscop-frontend-guide\\src\\components\\Footer.tsx",
            "fileType": ".tsx",
            "linesAdded": 39,
            "linesRemoved": 0,
            "projectName": "eventscop-frontend-guide (Workspace)",
            "content": {
              "added": [],
              "removed": []
            },
            "duration": 0,
            "language": "tsx"
          },
          {
            "timestamp": "2025-11-28T03:00:02.602Z",
            "fileName": "c:\\Mes Projets\\EventScop\\eventscop-frontend-guide\\src\\components\\Footer.tsx",
            "fileType": ".tsx",
            "linesAdded": 0,
            "linesRemoved": 39,
            "projectName": "eventscop-frontend-guide (Workspace)",
            "content": {
              "added": [],
              "removed": []
            },
            "duration": 4,
            "language": "tsx"
          }
        ],
        "c:\\Mes Projets\\EventScop\\eventscop-frontend-guide\\.next\\package.json": [
          {
            "timestamp": "2025-11-28T02:07:01.633Z",
            "fileName": "c:\\Mes Projets\\EventScop\\eventscop-frontend-guide\\.next\\package.json",
            "fileType": ".json",
            "linesAdded": 1,
            "linesRemoved": 0,
            "projectName": "eventscop-frontend-guide (Workspace)",
            "content": {
              "added": [],
              "removed": []
            },
            "duration": 1,
            "language": "json"
          },
          {
            "timestamp": "2025-11-28T13:50:44.161Z",
            "fileName": "c:\\Mes Projets\\EventScop\\eventscop-frontend-guide\\.next\\package.json",
            "fileType": ".json",
            "linesAdded": 3,
            "linesRemoved": 0,
            "projectName": "eventscop-frontend-guide (Workspace)",
            "content": {
              "added": [],
              "removed": []
            },
            "duration": 0,
            "language": "json"
          },
          {
            "timestamp": "2025-11-28T13:50:48.720Z",
            "fileName": "c:\\Mes Projets\\EventScop\\eventscop-frontend-guide\\.next\\package.json",
            "fileType": ".json",
            "linesAdded": 0,
            "linesRemoved": 2,
            "projectName": "eventscop-frontend-guide (Workspace)",
            "content": {
              "added": [],
              "removed": []
            },
            "duration": 1,
            "language": "json"
          }
        ],
        "c:\\Mes Projets\\EventScop\\eventscop-frontend-guide\\src\\i18n\\routing.ts": [
          {
            "timestamp": "2025-11-28T03:03:29.550Z",
            "fileName": "c:\\Mes Projets\\EventScop\\eventscop-frontend-guide\\src\\i18n\\routing.ts",
            "fileType": ".ts",
            "linesAdded": 415,
            "linesRemoved": 0,
            "projectName": "eventscop-frontend-guide (Workspace)",
            "content": {
              "added": [],
              "removed": []
            },
            "duration": 4,
            "language": "ts"
          }
        ],
        "c:\\Mes Projets\\EventScop\\eventscop-frontend-guide\\package.json": [
          {
            "timestamp": "2025-11-28T12:01:47.752Z",
            "fileName": "c:\\Mes Projets\\EventScop\\eventscop-frontend-guide\\package.json",
            "fileType": ".json",
            "linesAdded": 123,
            "linesRemoved": 0,
            "projectName": "eventscop-frontend-guide (Workspace)",
            "content": {
              "added": [],
              "removed": []
            },
            "duration": 0,
            "language": "json"
          },
          {
            "timestamp": "2025-11-28T16:06:18.859Z",
            "fileName": "c:\\Mes Projets\\EventScop\\eventscop-frontend-guide\\package.json",
            "fileType": ".json",
            "linesAdded": 122,
            "linesRemoved": 0,
            "projectName": "eventscop-frontend-guide (Workspace)",
            "content": {
              "added": [],
              "removed": []
            },
            "duration": 1,
            "language": "json"
          },
          {
            "timestamp": "2025-11-28T16:06:32.091Z",
            "fileName": "c:\\Mes Projets\\EventScop\\eventscop-frontend-guide\\package.json",
            "fileType": ".json",
            "linesAdded": 1,
            "linesRemoved": 0,
            "projectName": "eventscop-frontend-guide (Workspace)",
            "content": {
              "added": [],
              "removed": []
            },
            "duration": 1,
            "language": "json"
          }
        ],
        "c:\\Mes Projets\\EventScop\\eventscop-frontend-guide\\src\\types\\format.ts": [
          {
            "timestamp": "2025-11-28T12:05:30.369Z",
            "fileName": "c:\\Mes Projets\\EventScop\\eventscop-frontend-guide\\src\\types\\format.ts",
            "fileType": ".ts",
            "linesAdded": 16,
            "linesRemoved": 0,
            "projectName": "eventscop-frontend-guide (Workspace)",
            "content": {
              "added": [],
              "removed": []
            },
            "duration": 4,
            "language": "ts"
          },
          {
            "timestamp": "2025-11-28T12:05:36.248Z",
            "fileName": "c:\\Mes Projets\\EventScop\\eventscop-frontend-guide\\src\\types\\format.ts",
            "fileType": ".ts",
            "linesAdded": 2,
            "linesRemoved": 0,
            "projectName": "eventscop-frontend-guide (Workspace)",
            "content": {
              "added": [],
              "removed": []
            },
            "duration": 1,
            "language": "ts"
          },
          {
            "timestamp": "2025-11-28T12:06:04.059Z",
            "fileName": "c:\\Mes Projets\\EventScop\\eventscop-frontend-guide\\src\\types\\format.ts",
            "fileType": ".ts",
            "linesAdded": 0,
            "linesRemoved": 1,
            "projectName": "eventscop-frontend-guide (Workspace)",
            "content": {
              "added": [],
              "removed": []
            },
            "duration": 1,
            "language": "ts"
          },
          {
            "timestamp": "2025-11-28T12:06:54.545Z",
            "fileName": "c:\\Mes Projets\\EventScop\\eventscop-frontend-guide\\src\\types\\format.ts",
            "fileType": ".ts",
            "linesAdded": 0,
            "linesRemoved": 1,
            "projectName": "eventscop-frontend-guide (Workspace)",
            "content": {
              "added": [],
              "removed": []
            },
            "duration": 1,
            "language": "ts"
          }
        ],
        "c:\\Mes Projets\\EventScop\\eventscop-frontend-guide\\lefthook.yml": [
          {
            "timestamp": "2025-11-28T12:07:20.184Z",
            "fileName": "c:\\Mes Projets\\EventScop\\eventscop-frontend-guide\\lefthook.yml",
            "fileType": ".yml",
            "linesAdded": 22,
            "linesRemoved": 0,
            "projectName": "eventscop-frontend-guide (Workspace)",
            "content": {
              "added": [],
              "removed": []
            },
            "duration": 1,
            "language": "yml"
          },
          {
            "timestamp": "2025-11-28T12:07:21.462Z",
            "fileName": "c:\\Mes Projets\\EventScop\\eventscop-frontend-guide\\lefthook.yml",
            "fileType": ".yml",
            "linesAdded": 0,
            "linesRemoved": 9,
            "projectName": "eventscop-frontend-guide (Workspace)",
            "content": {
              "added": [],
              "removed": []
            },
            "duration": 1,
            "language": "yml"
          },
          {
            "timestamp": "2025-11-28T12:07:31.047Z",
            "fileName": "c:\\Mes Projets\\EventScop\\eventscop-frontend-guide\\lefthook.yml",
            "fileType": ".yml",
            "linesAdded": 9,
            "linesRemoved": 0,
            "projectName": "eventscop-frontend-guide (Workspace)",
            "content": {
              "added": [],
              "removed": []
            },
            "duration": 1,
            "language": "yml"
          }
        ],
        "c:\\Mes Projets\\EventScop\\eventscop-frontend-guide\\.next\\types\\package.json": [
          {
            "timestamp": "2025-11-28T12:59:14.623Z",
            "fileName": "c:\\Mes Projets\\EventScop\\eventscop-frontend-guide\\.next\\types\\package.json",
            "fileType": ".json",
            "linesAdded": 1,
            "linesRemoved": 0,
            "projectName": "eventscop-frontend-guide (Workspace)",
            "content": {
              "added": [],
              "removed": []
            },
            "duration": 0,
            "language": "json"
          },
          {
            "timestamp": "2025-11-28T13:42:23.400Z",
            "fileName": "c:\\Mes Projets\\EventScop\\eventscop-frontend-guide\\.next\\types\\package.json",
            "fileType": ".json",
            "linesAdded": 1,
            "linesRemoved": 0,
            "projectName": "eventscop-frontend-guide (Workspace)",
            "content": {
              "added": [],
              "removed": []
            },
            "duration": 0,
            "language": "json"
          }
        ],
        "c:\\Mes Projets\\EventScop\\eventscop-frontend-guide\\src\\i18n\\locales\\fr.json": [
          {
            "timestamp": "2025-11-28T14:42:01.399Z",
            "fileName": "c:\\Mes Projets\\EventScop\\eventscop-frontend-guide\\src\\i18n\\locales\\fr.json",
            "fileType": ".json",
            "linesAdded": 1986,
            "linesRemoved": 0,
            "projectName": "eventscop-frontend-guide (Workspace)",
            "content": {
              "added": [],
              "removed": []
            },
            "duration": 0,
            "language": "json"
          },
          {
            "timestamp": "2025-11-28T16:06:07.566Z",
            "fileName": "c:\\Mes Projets\\EventScop\\eventscop-frontend-guide\\src\\i18n\\locales\\fr.json",
            "fileType": ".json",
            "linesAdded": 0,
            "linesRemoved": 4,
            "projectName": "eventscop-frontend-guide (Workspace)",
            "content": {
              "added": [],
              "removed": []
            },
            "duration": 0,
            "language": "json"
          },
          {
            "timestamp": "2025-11-28T16:06:18.867Z",
            "fileName": "c:\\Mes Projets\\EventScop\\eventscop-frontend-guide\\src\\i18n\\locales\\fr.json",
            "fileType": ".json",
            "linesAdded": 4,
            "linesRemoved": 0,
            "projectName": "eventscop-frontend-guide (Workspace)",
            "content": {
              "added": [],
              "removed": []
            },
            "duration": 1,
            "language": "json"
          },
          {
            "timestamp": "2025-11-28T16:06:32.083Z",
            "fileName": "c:\\Mes Projets\\EventScop\\eventscop-frontend-guide\\src\\i18n\\locales\\fr.json",
            "fileType": ".json",
            "linesAdded": 0,
            "linesRemoved": 4,
            "projectName": "eventscop-frontend-guide (Workspace)",
            "content": {
              "added": [],
              "removed": []
            },
            "duration": 1,
            "language": "json"
          }
        ],
        "c:\\Mes Projets\\EventScop\\eventscop-frontend-guide\\scripts\\review.ts": [
          {
            "timestamp": "2025-11-28T16:17:36.389Z",
            "fileName": "c:\\Mes Projets\\EventScop\\eventscop-frontend-guide\\scripts\\review.ts",
            "fileType": ".ts",
            "linesAdded": 74,
            "linesRemoved": 0,
            "projectName": "eventscop-frontend-guide (Workspace)",
            "content": {
              "added": [],
              "removed": []
            },
            "duration": 0,
            "language": "ts"
          },
          {
            "timestamp": "2025-11-28T16:17:37.053Z",
            "fileName": "c:\\Mes Projets\\EventScop\\eventscop-frontend-guide\\scripts\\review.ts",
            "fileType": ".ts",
            "linesAdded": 28,
            "linesRemoved": 0,
            "projectName": "eventscop-frontend-guide (Workspace)",
            "content": {
              "added": [],
              "removed": []
            },
            "duration": 1,
            "language": "ts"
          },
          {
            "timestamp": "2025-11-28T16:19:43.962Z",
            "fileName": "c:\\Mes Projets\\EventScop\\eventscop-frontend-guide\\scripts\\review.ts",
            "fileType": ".ts",
            "linesAdded": 0,
            "linesRemoved": 28,
            "projectName": "eventscop-frontend-guide (Workspace)",
            "content": {
              "added": [],
              "removed": []
            },
            "duration": 3,
            "language": "ts"
          },
          {
            "timestamp": "2025-11-28T16:19:48.534Z",
            "fileName": "c:\\Mes Projets\\EventScop\\eventscop-frontend-guide\\scripts\\review.ts",
            "fileType": ".ts",
            "linesAdded": 28,
            "linesRemoved": 0,
            "projectName": "eventscop-frontend-guide (Workspace)",
            "content": {
              "added": [],
              "removed": []
            },
            "duration": 1,
            "language": "ts"
          }
        ]
      },
      "languageStats": {
        "tsx": 0
      },
      "changeFrequency": {
        "2": 0
      },
      "topFiles": [
        "c:\\Mes Projets\\EventScop\\eventscop-frontend-guide\\src\\components\\brief\\steps\\RecapConfirmation.tsx"
      ],
      "averageChangeSize": 64
    }
  },
  "totalActiveTime": 0,
  "totalProjects": 1,
  "totalFiles": 1,
  "mostActiveHours": [
    0
  ],
  "mostUsedLanguages": [
    "asp"
  ]
}